{
"meta":{"test_sets":[],"test_metrics":[],"learn_metrics":[{"best_value":"Min","name":"Logloss"}],"launch_mode":"Train","parameters":"","iteration_count":1000,"learn_sets":["learn"],"name":"experiment"},
"iterations":[
{"learn":[0.6848258335],"iteration":0,"passed_time":0.002475640166,"remaining_time":2.473164526},
{"learn":[0.6766158799],"iteration":1,"passed_time":0.004836862424,"remaining_time":2.41359435},
{"learn":[0.6691051481],"iteration":2,"passed_time":0.007110417288,"remaining_time":2.363028679},
{"learn":[0.6624658267],"iteration":3,"passed_time":0.009462826282,"remaining_time":2.356243744},
{"learn":[0.6562331574],"iteration":4,"passed_time":0.01175206677,"remaining_time":2.338661288},
{"learn":[0.6487333077],"iteration":5,"passed_time":0.01445201278,"remaining_time":2.394216784},
{"learn":[0.6423265662],"iteration":6,"passed_time":0.01723714764,"remaining_time":2.445212516},
{"learn":[0.6368098934],"iteration":7,"passed_time":0.02008940269,"remaining_time":2.491085934},
{"learn":[0.6298795284],"iteration":8,"passed_time":0.02316771738,"remaining_time":2.551023103},
{"learn":[0.6225694656],"iteration":9,"passed_time":0.02642270442,"remaining_time":2.615847737},
{"learn":[0.6159385109],"iteration":10,"passed_time":0.02892224458,"remaining_time":2.600372717},
{"learn":[0.6085117082],"iteration":11,"passed_time":0.03131714707,"remaining_time":2.578445109},
{"learn":[0.6017519818],"iteration":12,"passed_time":0.03383742489,"remaining_time":2.569041413},
{"learn":[0.5962660125],"iteration":13,"passed_time":0.03659879367,"remaining_time":2.577600754},
{"learn":[0.5902130699],"iteration":14,"passed_time":0.03957042621,"remaining_time":2.598457988},
{"learn":[0.5839398599],"iteration":15,"passed_time":0.04238847676,"remaining_time":2.60689132},
{"learn":[0.5783067237],"iteration":16,"passed_time":0.04489382041,"remaining_time":2.595919145},
{"learn":[0.5733563291],"iteration":17,"passed_time":0.0472083405,"remaining_time":2.575477243},
{"learn":[0.5695245305],"iteration":18,"passed_time":0.04859559572,"remaining_time":2.509067337},
{"learn":[0.5642585529],"iteration":19,"passed_time":0.05137055554,"remaining_time":2.517157222},
{"learn":[0.5594877897],"iteration":20,"passed_time":0.05376011005,"remaining_time":2.50624513},
{"learn":[0.5548590707],"iteration":21,"passed_time":0.05608628222,"remaining_time":2.493290182},
{"learn":[0.5495624551],"iteration":22,"passed_time":0.0584103495,"remaining_time":2.481170064},
{"learn":[0.5442751831],"iteration":23,"passed_time":0.06091502661,"remaining_time":2.477211082},
{"learn":[0.5399707004],"iteration":24,"passed_time":0.0637400684,"remaining_time":2.485862668},
{"learn":[0.5348929452],"iteration":25,"passed_time":0.06673418821,"remaining_time":2.499965358},
{"learn":[0.5307247751],"iteration":26,"passed_time":0.06911137397,"remaining_time":2.490569143},
{"learn":[0.5264286105],"iteration":27,"passed_time":0.0717478775,"remaining_time":2.490676319},
{"learn":[0.5232034525],"iteration":28,"passed_time":0.07374871343,"remaining_time":2.469310371},
{"learn":[0.5186892382],"iteration":29,"passed_time":0.07616217852,"remaining_time":2.462577105},
{"learn":[0.5139501244],"iteration":30,"passed_time":0.07880303718,"remaining_time":2.46323042},
{"learn":[0.5099823807],"iteration":31,"passed_time":0.08106455406,"remaining_time":2.45220276},
{"learn":[0.5058478193],"iteration":32,"passed_time":0.083793723,"remaining_time":2.455410004},
{"learn":[0.5013747269],"iteration":33,"passed_time":0.08680602006,"remaining_time":2.466312217},
{"learn":[0.4971029076],"iteration":34,"passed_time":0.08921291989,"remaining_time":2.459727648},
{"learn":[0.4930990159],"iteration":35,"passed_time":0.09212587604,"remaining_time":2.466926236},
{"learn":[0.4887021275],"iteration":36,"passed_time":0.09511814154,"remaining_time":2.475642441},
{"learn":[0.4850100125],"iteration":37,"passed_time":0.09738558219,"remaining_time":2.465392897},
{"learn":[0.4821176108],"iteration":38,"passed_time":0.09896420085,"remaining_time":2.438579411},
{"learn":[0.4780559637],"iteration":39,"passed_time":0.1020364531,"remaining_time":2.448874875},
{"learn":[0.4739289563],"iteration":40,"passed_time":0.1048326278,"remaining_time":2.452060733},
{"learn":[0.4705206807],"iteration":41,"passed_time":0.1074957833,"remaining_time":2.451927628},
{"learn":[0.4666404447],"iteration":42,"passed_time":0.1099434278,"remaining_time":2.446880475},
{"learn":[0.4639008498],"iteration":43,"passed_time":0.1123566975,"remaining_time":2.441204608},
{"learn":[0.4604120329],"iteration":44,"passed_time":0.1146576967,"remaining_time":2.433291118},
{"learn":[0.4572851492],"iteration":45,"passed_time":0.1172165993,"remaining_time":2.430970341},
{"learn":[0.4542608625],"iteration":46,"passed_time":0.1196432249,"remaining_time":2.425957306},
{"learn":[0.451196641],"iteration":47,"passed_time":0.1220207356,"remaining_time":2.420077923},
{"learn":[0.4486335662],"iteration":48,"passed_time":0.124261906,"remaining_time":2.41169536},
{"learn":[0.446070695],"iteration":49,"passed_time":0.1262799077,"remaining_time":2.399318246},
{"learn":[0.443249326],"iteration":50,"passed_time":0.1283062972,"remaining_time":2.387503452},
{"learn":[0.4401181872],"iteration":51,"passed_time":0.1304981987,"remaining_time":2.379082545},
{"learn":[0.4389876379],"iteration":52,"passed_time":0.1318168174,"remaining_time":2.355292945},
{"learn":[0.4365014046],"iteration":53,"passed_time":0.1343304303,"remaining_time":2.35327013},
{"learn":[0.4341550411],"iteration":54,"passed_time":0.1367755038,"remaining_time":2.350051838},
{"learn":[0.4313980487],"iteration":55,"passed_time":0.1391721749,"remaining_time":2.346045234},
{"learn":[0.4297740625],"iteration":56,"passed_time":0.1406197848,"remaining_time":2.326393984},
{"learn":[0.4273635215],"iteration":57,"passed_time":0.1428351444,"remaining_time":2.319839759},
{"learn":[0.4250781119],"iteration":58,"passed_time":0.1449657721,"remaining_time":2.312081212},
{"learn":[0.4227441007],"iteration":59,"passed_time":0.1481696294,"remaining_time":2.321324194},
{"learn":[0.4203631342],"iteration":60,"passed_time":0.1506085035,"remaining_time":2.318383358},
{"learn":[0.4175600497],"iteration":61,"passed_time":0.1527608467,"remaining_time":2.311123777},
{"learn":[0.4148769308],"iteration":62,"passed_time":0.1549073763,"remaining_time":2.303939866},
{"learn":[0.4124575935],"iteration":63,"passed_time":0.1570184334,"remaining_time":2.296394588},
{"learn":[0.4096655729],"iteration":64,"passed_time":0.1591322419,"remaining_time":2.289056095},
{"learn":[0.407846227],"iteration":65,"passed_time":0.1613118334,"remaining_time":2.282806854},
{"learn":[0.405535829],"iteration":66,"passed_time":0.1802322939,"remaining_time":2.509801943},
{"learn":[0.4047614058],"iteration":67,"passed_time":0.1813781674,"remaining_time":2.485947824},
{"learn":[0.4024444946],"iteration":68,"passed_time":0.1836220032,"remaining_time":2.477566449},
{"learn":[0.3999758141],"iteration":69,"passed_time":0.1860662449,"remaining_time":2.472022967},
{"learn":[0.397529034],"iteration":70,"passed_time":0.1884472695,"remaining_time":2.465739625},
{"learn":[0.3949287134],"iteration":71,"passed_time":0.1909632279,"remaining_time":2.461303826},
{"learn":[0.3932037343],"iteration":72,"passed_time":0.1933778957,"remaining_time":2.455634375},
{"learn":[0.3907282123],"iteration":73,"passed_time":0.1956360047,"remaining_time":2.448093789},
{"learn":[0.3889283075],"iteration":74,"passed_time":0.1981030399,"remaining_time":2.443270825},
{"learn":[0.3865315231],"iteration":75,"passed_time":0.2003540459,"remaining_time":2.4358834},
{"learn":[0.384522212],"iteration":76,"passed_time":0.2025357832,"remaining_time":2.427799063},
{"learn":[0.3836770816],"iteration":77,"passed_time":0.2039007703,"remaining_time":2.410211669},
{"learn":[0.3815884213],"iteration":78,"passed_time":0.2058764026,"remaining_time":2.40015401},
{"learn":[0.380103502],"iteration":79,"passed_time":0.2080710104,"remaining_time":2.392816619},
{"learn":[0.3786225065],"iteration":80,"passed_time":0.2100992845,"remaining_time":2.383719043},
{"learn":[0.3780633701],"iteration":81,"passed_time":0.2115674573,"remaining_time":2.368523485},
{"learn":[0.3762109827],"iteration":82,"passed_time":0.2139300892,"remaining_time":2.363540865},
{"learn":[0.3740208657],"iteration":83,"passed_time":0.2161753124,"remaining_time":2.357340311},
{"learn":[0.3721453422],"iteration":84,"passed_time":0.2184164226,"remaining_time":2.35118855},
{"learn":[0.3705334726],"iteration":85,"passed_time":0.2206877568,"remaining_time":2.34544895},
{"learn":[0.3695239366],"iteration":86,"passed_time":0.2221735004,"remaining_time":2.331544895},
{"learn":[0.3675469104],"iteration":87,"passed_time":0.2243021376,"remaining_time":2.324585789},
{"learn":[0.3656754509],"iteration":88,"passed_time":0.2264945939,"remaining_time":2.318388484},
{"learn":[0.3636984074],"iteration":89,"passed_time":0.2290026096,"remaining_time":2.315470831},
{"learn":[0.3621472304],"iteration":90,"passed_time":0.2313140074,"remaining_time":2.310598162},
{"learn":[0.360422072],"iteration":91,"passed_time":0.2334008383,"remaining_time":2.303564795},
{"learn":[0.3591455548],"iteration":92,"passed_time":0.2354530536,"remaining_time":2.296300211},
{"learn":[0.3575281777],"iteration":93,"passed_time":0.2375315456,"remaining_time":2.289399791},
{"learn":[0.3559153359],"iteration":94,"passed_time":0.2396882984,"remaining_time":2.283346422},
{"learn":[0.3547931179],"iteration":95,"passed_time":0.2417832022,"remaining_time":2.276791821},
{"learn":[0.3531171985],"iteration":96,"passed_time":0.2440569684,"remaining_time":2.271994252},
{"learn":[0.3516747963],"iteration":97,"passed_time":0.246273129,"remaining_time":2.266717983},
{"learn":[0.3497903431],"iteration":98,"passed_time":0.2485344755,"remaining_time":2.261914772},
{"learn":[0.3481361607],"iteration":99,"passed_time":0.2509605348,"remaining_time":2.258644814},
{"learn":[0.346967842],"iteration":100,"passed_time":0.2534355029,"remaining_time":2.255826902},
{"learn":[0.3459381694],"iteration":101,"passed_time":0.2557673132,"remaining_time":2.251755365},
{"learn":[0.344570165],"iteration":102,"passed_time":0.258541387,"remaining_time":2.251569167},
{"learn":[0.3433831742],"iteration":103,"passed_time":0.2613965074,"remaining_time":2.252031448},
{"learn":[0.3422574691],"iteration":104,"passed_time":0.263618839,"remaining_time":2.24703677},
{"learn":[0.3413212029],"iteration":105,"passed_time":0.2658030813,"remaining_time":2.241773157},
{"learn":[0.3397157444],"iteration":106,"passed_time":0.2683864262,"remaining_time":2.239897931},
{"learn":[0.3385279337],"iteration":107,"passed_time":0.2704609083,"remaining_time":2.233806762},
{"learn":[0.3372427336],"iteration":108,"passed_time":0.2725633045,"remaining_time":2.228017471},
{"learn":[0.3359341652],"iteration":109,"passed_time":0.2747732373,"remaining_time":2.223165284},
{"learn":[0.3351475965],"iteration":110,"passed_time":0.2769086611,"remaining_time":2.217763961},
{"learn":[0.333838511],"iteration":111,"passed_time":0.279000674,"remaining_time":2.212076772},
{"learn":[0.3324129028],"iteration":112,"passed_time":0.2816523027,"remaining_time":2.210845951},
{"learn":[0.331274258],"iteration":113,"passed_time":0.2837863883,"remaining_time":2.205567895},
{"learn":[0.3301802938],"iteration":114,"passed_time":0.2860289462,"remaining_time":2.201179281},
{"learn":[0.3285699755],"iteration":115,"passed_time":0.2881001799,"remaining_time":2.195522061},
{"learn":[0.3272460552],"iteration":116,"passed_time":0.2902506695,"remaining_time":2.190524284},
{"learn":[0.3259627922],"iteration":117,"passed_time":0.2923584883,"remaining_time":2.185255819},
{"learn":[0.3248331492],"iteration":118,"passed_time":0.2946265704,"remaining_time":2.181226963},
{"learn":[0.3240331483],"iteration":119,"passed_time":0.2968789611,"remaining_time":2.177112381},
{"learn":[0.323140701],"iteration":120,"passed_time":0.2991035923,"remaining_time":2.172826922},
{"learn":[0.3225164415],"iteration":121,"passed_time":0.3011731579,"remaining_time":2.167459284},
{"learn":[0.3217037362],"iteration":122,"passed_time":0.3032749786,"remaining_time":2.162375254},
{"learn":[0.3205744971],"iteration":123,"passed_time":0.3055612029,"remaining_time":2.158642047},
{"learn":[0.3197329461],"iteration":124,"passed_time":0.3079777157,"remaining_time":2.15584401},
{"learn":[0.3192097437],"iteration":125,"passed_time":0.3094563522,"remaining_time":2.146546443},
{"learn":[0.3179726201],"iteration":126,"passed_time":0.3114726942,"remaining_time":2.141068205},
{"learn":[0.316965097],"iteration":127,"passed_time":0.3134908153,"remaining_time":2.135656179},
{"learn":[0.3159579522],"iteration":128,"passed_time":0.3154697809,"remaining_time":2.130032397},
{"learn":[0.3146859695],"iteration":129,"passed_time":0.3174827737,"remaining_time":2.124692409},
{"learn":[0.3138518323],"iteration":130,"passed_time":0.319479095,"remaining_time":2.119292622},
{"learn":[0.3129610576],"iteration":131,"passed_time":0.3214517755,"remaining_time":2.113788948},
{"learn":[0.3122066736],"iteration":132,"passed_time":0.3237400487,"remaining_time":2.110395656},
{"learn":[0.3112163903],"iteration":133,"passed_time":0.3257813596,"remaining_time":2.105422816},
{"learn":[0.3102708307],"iteration":134,"passed_time":0.3282096291,"remaining_time":2.102972808},
{"learn":[0.3094801708],"iteration":135,"passed_time":0.3303789967,"remaining_time":2.098878332},
{"learn":[0.3088152264],"iteration":136,"passed_time":0.3327069831,"remaining_time":2.095811142},
{"learn":[0.3081593443],"iteration":137,"passed_time":0.3347667705,"remaining_time":2.091079393},
{"learn":[0.3073574363],"iteration":138,"passed_time":0.3368596204,"remaining_time":2.086590886},
{"learn":[0.306560683],"iteration":139,"passed_time":0.3392137926,"remaining_time":2.083741869},
{"learn":[0.3054245977],"iteration":140,"passed_time":0.3413595596,"remaining_time":2.079630225},
{"learn":[0.3048172154],"iteration":141,"passed_time":0.3433120746,"remaining_time":2.074378592},
{"learn":[0.3039277271],"iteration":142,"passed_time":0.3454013155,"remaining_time":2.069992499},
{"learn":[0.3031047419],"iteration":143,"passed_time":0.3479663779,"remaining_time":2.068466802},
{"learn":[0.3023976142],"iteration":144,"passed_time":0.3500779956,"remaining_time":2.064253008},
{"learn":[0.3017263952],"iteration":145,"passed_time":0.3522142412,"remaining_time":2.060212069},
{"learn":[0.3013467675],"iteration":146,"passed_time":0.3547595428,"remaining_time":2.05857068},
{"learn":[0.3004833229],"iteration":147,"passed_time":0.3572810039,"remaining_time":2.056779833},
{"learn":[0.2994944712],"iteration":148,"passed_time":0.3597029036,"remaining_time":2.054410543},
{"learn":[0.2987308152],"iteration":149,"passed_time":0.3622195235,"remaining_time":2.0525773},
{"learn":[0.298028155],"iteration":150,"passed_time":0.3644499681,"remaining_time":2.04912598},
{"learn":[0.2975170154],"iteration":151,"passed_time":0.3668570183,"remaining_time":2.046675997},
{"learn":[0.2967756858],"iteration":152,"passed_time":0.3693553398,"remaining_time":2.044731848},
{"learn":[0.29600416],"iteration":153,"passed_time":0.3719637188,"remaining_time":2.043385104},
{"learn":[0.2952407224],"iteration":154,"passed_time":0.3742601368,"remaining_time":2.040321391},
{"learn":[0.2945398682],"iteration":155,"passed_time":0.3767366685,"remaining_time":2.038241976},
{"learn":[0.2935905668],"iteration":156,"passed_time":0.3793038951,"remaining_time":2.036644482},
{"learn":[0.2930922653],"iteration":157,"passed_time":0.3816844846,"remaining_time":2.034040102},
{"learn":[0.2925802298],"iteration":158,"passed_time":0.3837184932,"remaining_time":2.029605364},
{"learn":[0.2920349919],"iteration":159,"passed_time":0.3858872345,"remaining_time":2.025907981},
{"learn":[0.2914187408],"iteration":160,"passed_time":0.3882042239,"remaining_time":2.023002136},
{"learn":[0.2907532572],"iteration":161,"passed_time":0.3902922425,"remaining_time":2.018919131},
{"learn":[0.2900678289],"iteration":162,"passed_time":0.3923392708,"remaining_time":2.014650121},
{"learn":[0.2896229067],"iteration":163,"passed_time":0.3943267849,"remaining_time":2.01010483},
{"learn":[0.2890636488],"iteration":164,"passed_time":0.3965079645,"remaining_time":2.006570608},
{"learn":[0.2888068097],"iteration":165,"passed_time":0.3980767612,"remaining_time":1.999976017},
{"learn":[0.2880024056],"iteration":166,"passed_time":0.4001226418,"remaining_time":1.995821321},
{"learn":[0.2873960868],"iteration":167,"passed_time":0.4025819585,"remaining_time":1.993739223},
{"learn":[0.2870349905],"iteration":168,"passed_time":0.404666494,"remaining_time":1.989809802},
{"learn":[0.2864512326],"iteration":169,"passed_time":0.4066926087,"remaining_time":1.985616854},
{"learn":[0.2858050805],"iteration":170,"passed_time":0.4088734029,"remaining_time":1.982199129},
{"learn":[0.2852225793],"iteration":171,"passed_time":0.4110940002,"remaining_time":1.978987396},
{"learn":[0.2842591027],"iteration":172,"passed_time":0.4133100559,"remaining_time":1.975765412},
{"learn":[0.283743265],"iteration":173,"passed_time":0.4153671125,"remaining_time":1.971800201},
{"learn":[0.2830492622],"iteration":174,"passed_time":0.417698156,"remaining_time":1.96914845},
{"learn":[0.2821132548],"iteration":175,"passed_time":0.420166223,"remaining_time":1.967141862},
{"learn":[0.2815081115],"iteration":176,"passed_time":0.4224968204,"remaining_time":1.964490866},
{"learn":[0.2809540786],"iteration":177,"passed_time":0.4246693655,"remaining_time":1.961113587},
{"learn":[0.2803985211],"iteration":178,"passed_time":0.426938044,"remaining_time":1.958190694},
{"learn":[0.2794560788],"iteration":179,"passed_time":0.4290401805,"remaining_time":1.954516378},
{"learn":[0.2786460171],"iteration":180,"passed_time":0.4311999608,"remaining_time":1.951120265},
{"learn":[0.2778656529],"iteration":181,"passed_time":0.4334857692,"remaining_time":1.948304171},
{"learn":[0.2774002069],"iteration":182,"passed_time":0.4358134599,"remaining_time":1.945680856},
{"learn":[0.2769283012],"iteration":183,"passed_time":0.4378920516,"remaining_time":1.941956055},
{"learn":[0.2765390683],"iteration":184,"passed_time":0.4399788373,"remaining_time":1.938285148},
{"learn":[0.2760097097],"iteration":185,"passed_time":0.4422076081,"remaining_time":1.93525265},
{"learn":[0.2753437393],"iteration":186,"passed_time":0.4442890714,"remaining_time":1.931588316},
{"learn":[0.2749512749],"iteration":187,"passed_time":0.4465463791,"remaining_time":1.928700318},
{"learn":[0.2744195808],"iteration":188,"passed_time":0.4487356825,"remaining_time":1.925527188},
{"learn":[0.2739573443],"iteration":189,"passed_time":0.4509996802,"remaining_time":1.922682847},
{"learn":[0.273337088],"iteration":190,"passed_time":0.452955722,"remaining_time":1.918540205},
{"learn":[0.2729237132],"iteration":191,"passed_time":0.4551391724,"remaining_time":1.915377351},
{"learn":[0.2721944919],"iteration":192,"passed_time":0.4572368384,"remaining_time":1.911865951},
{"learn":[0.271582472],"iteration":193,"passed_time":0.4595715404,"remaining_time":1.909353926},
{"learn":[0.2711479833],"iteration":194,"passed_time":0.4618603958,"remaining_time":1.906654455},
{"learn":[0.2707014347],"iteration":195,"passed_time":0.4641309487,"remaining_time":1.903884096},
{"learn":[0.2701414124],"iteration":196,"passed_time":0.4664253011,"remaining_time":1.901215821},
{"learn":[0.2693607503],"iteration":197,"passed_time":0.4685303702,"remaining_time":1.897784631},
{"learn":[0.2687506201],"iteration":198,"passed_time":0.4705215035,"remaining_time":1.893908162},
{"learn":[0.2680443031],"iteration":199,"passed_time":0.4728144535,"remaining_time":1.891257814},
{"learn":[0.2673881309],"iteration":200,"passed_time":0.4752793882,"remaining_time":1.889294682},
{"learn":[0.2667613992],"iteration":201,"passed_time":0.4779533889,"remaining_time":1.888152497},
{"learn":[0.2662551273],"iteration":202,"passed_time":0.48019522,"remaining_time":1.885298475},
{"learn":[0.2659875296],"iteration":203,"passed_time":0.4824799108,"remaining_time":1.882617691},
{"learn":[0.2657061119],"iteration":204,"passed_time":0.484863938,"remaining_time":1.880326003},
{"learn":[0.2650621077],"iteration":205,"passed_time":0.4869624496,"remaining_time":1.876932937},
{"learn":[0.2645480426],"iteration":206,"passed_time":0.4890941355,"remaining_time":1.873679466},
{"learn":[0.2642001743],"iteration":207,"passed_time":0.4913064179,"remaining_time":1.870743668},
{"learn":[0.2636966671],"iteration":208,"passed_time":0.4936972955,"remaining_time":1.868490721},
{"learn":[0.2631877731],"iteration":209,"passed_time":0.4957846225,"remaining_time":1.865094532},
{"learn":[0.2625235853],"iteration":210,"passed_time":0.4982153569,"remaining_time":1.862994865},
{"learn":[0.2619172953],"iteration":211,"passed_time":0.500507966,"remaining_time":1.860378666},
{"learn":[0.2613911328],"iteration":212,"passed_time":0.5027961758,"remaining_time":1.857749251},
{"learn":[0.2609273052],"iteration":213,"passed_time":0.5049281115,"remaining_time":1.854549045},
{"learn":[0.2605354932],"iteration":214,"passed_time":0.5071399479,"remaining_time":1.851650507},
{"learn":[0.2600595945],"iteration":215,"passed_time":0.5092342369,"remaining_time":1.848331675},
{"learn":[0.2597263159],"iteration":216,"passed_time":0.5113075513,"remaining_time":1.844948445},
{"learn":[0.2592036683],"iteration":217,"passed_time":0.5140659381,"remaining_time":1.844034696},
{"learn":[0.2586978035],"iteration":218,"passed_time":0.5164658567,"remaining_time":1.841825727},
{"learn":[0.2585013705],"iteration":219,"passed_time":0.5187892073,"remaining_time":1.839343553},
{"learn":[0.258065794],"iteration":220,"passed_time":0.5215631604,"remaining_time":1.83845114},
{"learn":[0.2576515377],"iteration":221,"passed_time":0.5240287516,"remaining_time":1.836461121},
{"learn":[0.2573739375],"iteration":222,"passed_time":0.5264293017,"remaining_time":1.834240213},
{"learn":[0.2570416957],"iteration":223,"passed_time":0.5295034425,"remaining_time":1.834351212},
{"learn":[0.2565344031],"iteration":224,"passed_time":0.5325489568,"remaining_time":1.834335296},
{"learn":[0.2560899054],"iteration":225,"passed_time":0.5350740213,"remaining_time":1.832510144},
{"learn":[0.2557296018],"iteration":226,"passed_time":0.5374161812,"remaining_time":1.830055983},
{"learn":[0.2554222339],"iteration":227,"passed_time":0.5395096775,"remaining_time":1.826760838},
{"learn":[0.2551317882],"iteration":228,"passed_time":0.5415581728,"remaining_time":1.823324678},
{"learn":[0.2544887282],"iteration":229,"passed_time":0.5438328303,"remaining_time":1.820657736},
{"learn":[0.2540618559],"iteration":230,"passed_time":0.5462281482,"remaining_time":1.81839587},
{"learn":[0.2535539182],"iteration":231,"passed_time":0.54849357,"remaining_time":1.815702852},
{"learn":[0.253353597],"iteration":232,"passed_time":0.551076068,"remaining_time":1.814057271},
{"learn":[0.2528816288],"iteration":233,"passed_time":0.5535891997,"remaining_time":1.812176611},
{"learn":[0.2527065167],"iteration":234,"passed_time":0.5559641803,"remaining_time":1.809840842},
{"learn":[0.252342215],"iteration":235,"passed_time":0.5582823239,"remaining_time":1.807320743},
{"learn":[0.251963712],"iteration":236,"passed_time":0.5603488775,"remaining_time":1.803992378},
{"learn":[0.2515627948],"iteration":237,"passed_time":0.5631019621,"remaining_time":1.802872669},
{"learn":[0.2511903438],"iteration":238,"passed_time":0.5655393478,"remaining_time":1.800734074},
{"learn":[0.2508007852],"iteration":239,"passed_time":0.5678347935,"remaining_time":1.798143513},
{"learn":[0.2505003752],"iteration":240,"passed_time":0.5699548265,"remaining_time":1.79500296},
{"learn":[0.2502525998],"iteration":241,"passed_time":0.5719866286,"remaining_time":1.791594481},
{"learn":[0.2498364936],"iteration":242,"passed_time":0.5742117868,"remaining_time":1.788799682},
{"learn":[0.2494246174],"iteration":243,"passed_time":0.5765554747,"remaining_time":1.786376799},
{"learn":[0.249120769],"iteration":244,"passed_time":0.5790408018,"remaining_time":1.784391042},
{"learn":[0.2486098327],"iteration":245,"passed_time":0.5812457013,"remaining_time":1.781541702},
{"learn":[0.2481973783],"iteration":246,"passed_time":0.5832960732,"remaining_time":1.77822649},
{"learn":[0.2478753214],"iteration":247,"passed_time":0.5856703973,"remaining_time":1.775903785},
{"learn":[0.2474749189],"iteration":248,"passed_time":0.5881892423,"remaining_time":1.77401655},
{"learn":[0.2472318349],"iteration":249,"passed_time":0.5907216288,"remaining_time":1.772164886},
{"learn":[0.2469886227],"iteration":250,"passed_time":0.5935592348,"remaining_time":1.771218593},
{"learn":[0.2468053895],"iteration":251,"passed_time":0.5961036142,"remaining_time":1.769386918},
{"learn":[0.2466043985],"iteration":252,"passed_time":0.598353915,"remaining_time":1.766681322},
{"learn":[0.2462357766],"iteration":253,"passed_time":0.6007394452,"remaining_time":1.764376481},
{"learn":[0.246096775],"iteration":254,"passed_time":0.6029968475,"remaining_time":1.761696672},
{"learn":[0.2457583134],"iteration":255,"passed_time":0.6051765241,"remaining_time":1.758794273},
{"learn":[0.2454732681],"iteration":256,"passed_time":0.60726554,"remaining_time":1.755635394},
{"learn":[0.2450531672],"iteration":257,"passed_time":0.6097689292,"remaining_time":1.753676533},
{"learn":[0.2448112345],"iteration":258,"passed_time":0.611906533,"remaining_time":1.750666954},
{"learn":[0.2445585786],"iteration":259,"passed_time":0.6139913291,"remaining_time":1.747513783},
{"learn":[0.2442099079],"iteration":260,"passed_time":0.6162652699,"remaining_time":1.744904346},
{"learn":[0.2439166561],"iteration":261,"passed_time":0.6185758708,"remaining_time":1.742400735},
{"learn":[0.2435681303],"iteration":262,"passed_time":0.6207637658,"remaining_time":1.739554735},
{"learn":[0.2430913229],"iteration":263,"passed_time":0.6228667642,"remaining_time":1.736477039},
{"learn":[0.2425078385],"iteration":264,"passed_time":0.625222962,"remaining_time":1.73410897},
{"learn":[0.2421808155],"iteration":265,"passed_time":0.6275093322,"remaining_time":1.731548308},
{"learn":[0.2419515214],"iteration":266,"passed_time":0.6297098372,"remaining_time":1.728753973},
{"learn":[0.2415566348],"iteration":267,"passed_time":0.6316351426,"remaining_time":1.725212404},
{"learn":[0.2413021477],"iteration":268,"passed_time":0.6335706016,"remaining_time":1.721710445},
{"learn":[0.2409460406],"iteration":269,"passed_time":0.6354235587,"remaining_time":1.717997029},
{"learn":[0.2405272519],"iteration":270,"passed_time":0.6373383797,"remaining_time":1.71446376},
{"learn":[0.2402470486],"iteration":271,"passed_time":0.6392175278,"remaining_time":1.710846913},
{"learn":[0.239690309],"iteration":272,"passed_time":0.6417093194,"remaining_time":1.708874268},
{"learn":[0.2394291753],"iteration":273,"passed_time":0.6436856033,"remaining_time":1.705531927},
{"learn":[0.2391085582],"iteration":274,"passed_time":0.6456293014,"remaining_time":1.702113613},
{"learn":[0.2387506542],"iteration":275,"passed_time":0.6476804693,"remaining_time":1.698987898},
{"learn":[0.238555722],"iteration":276,"passed_time":0.6495687085,"remaining_time":1.69544468},
{"learn":[0.2381459624],"iteration":277,"passed_time":0.6514709503,"remaining_time":1.691949734},
{"learn":[0.2378578446],"iteration":278,"passed_time":0.6533649729,"remaining_time":1.688444966},
{"learn":[0.2374031492],"iteration":279,"passed_time":0.6552192431,"remaining_time":1.684849482},
{"learn":[0.2370137567],"iteration":280,"passed_time":0.6574277067,"remaining_time":1.682172673},
{"learn":[0.2366218747],"iteration":281,"passed_time":0.659716933,"remaining_time":1.679704815},
{"learn":[0.236341681],"iteration":282,"passed_time":0.6616589271,"remaining_time":1.676358483},
{"learn":[0.2360059325],"iteration":283,"passed_time":0.6636076169,"remaining_time":1.673038921},
{"learn":[0.2355387157],"iteration":284,"passed_time":0.6655335637,"remaining_time":1.669671923},
{"learn":[0.2352100764],"iteration":285,"passed_time":0.6674933893,"remaining_time":1.66639958},
{"learn":[0.2348159713],"iteration":286,"passed_time":0.6694469904,"remaining_time":1.663120921},
{"learn":[0.234606012],"iteration":287,"passed_time":0.6714244019,"remaining_time":1.659910327},
{"learn":[0.2341269048],"iteration":288,"passed_time":0.6737364463,"remaining_time":1.657531534},
{"learn":[0.2339384662],"iteration":289,"passed_time":0.6757678081,"remaining_time":1.654466013},
{"learn":[0.2336387511],"iteration":290,"passed_time":0.6777171494,"remaining_time":1.651207763},
{"learn":[0.2332095584],"iteration":291,"passed_time":0.6796178576,"remaining_time":1.647840559},
{"learn":[0.2326757693],"iteration":292,"passed_time":0.6815352345,"remaining_time":1.644523586},
{"learn":[0.2323171328],"iteration":293,"passed_time":0.6834472891,"remaining_time":1.641203354},
{"learn":[0.2320626525],"iteration":294,"passed_time":0.6853325614,"remaining_time":1.637828664},
{"learn":[0.231490706],"iteration":295,"passed_time":0.6872903673,"remaining_time":1.634636549},
{"learn":[0.2313582787],"iteration":296,"passed_time":0.6893306148,"remaining_time":1.631647886},
{"learn":[0.2309793397],"iteration":297,"passed_time":0.6914538444,"remaining_time":1.62886107},
{"learn":[0.2305230693],"iteration":298,"passed_time":0.6933622304,"remaining_time":1.625574995},
{"learn":[0.2300183841],"iteration":299,"passed_time":0.6952862228,"remaining_time":1.62233452},
{"learn":[0.2299011536],"iteration":300,"passed_time":0.6971661226,"remaining_time":1.619000398},
{"learn":[0.2297189652],"iteration":301,"passed_time":0.6990546524,"remaining_time":1.615695852},
{"learn":[0.2295191088],"iteration":302,"passed_time":0.7009446056,"remaining_time":1.612403928},
{"learn":[0.2292223678],"iteration":303,"passed_time":0.70290784,"remaining_time":1.609289002},
{"learn":[0.2289397399],"iteration":304,"passed_time":0.7049129208,"remaining_time":1.606276983},
{"learn":[0.2287084139],"iteration":305,"passed_time":0.7068506049,"remaining_time":1.603118692},
{"learn":[0.2285342651],"iteration":306,"passed_time":0.7088445498,"remaining_time":1.600095352},
{"learn":[0.2283693656],"iteration":307,"passed_time":0.7107158296,"remaining_time":1.596803098},
{"learn":[0.228014334],"iteration":308,"passed_time":0.7126208679,"remaining_time":1.593595533},
{"learn":[0.2275956604],"iteration":309,"passed_time":0.714534877,"remaining_time":1.590416339},
{"learn":[0.2273092286],"iteration":310,"passed_time":0.7164269651,"remaining_time":1.587196717},
{"learn":[0.2269404266],"iteration":311,"passed_time":0.7183235437,"remaining_time":1.583995507},
{"learn":[0.2264400231],"iteration":312,"passed_time":0.7206241665,"remaining_time":1.581689464},
{"learn":[0.2260320538],"iteration":313,"passed_time":0.7229628377,"remaining_time":1.579466582},
{"learn":[0.2257757498],"iteration":314,"passed_time":0.724998685,"remaining_time":1.576584442},
{"learn":[0.2255498379],"iteration":315,"passed_time":0.7270044675,"remaining_time":1.573642581},
{"learn":[0.2250942058],"iteration":316,"passed_time":0.7289762108,"remaining_time":1.570633287},
{"learn":[0.2246563737],"iteration":317,"passed_time":0.7308612325,"remaining_time":1.56744453},
{"learn":[0.2243528499],"iteration":318,"passed_time":0.7327851145,"remaining_time":1.564346906},
{"learn":[0.2239446357],"iteration":319,"passed_time":0.7347070821,"remaining_time":1.56125255},
{"learn":[0.2236620289],"iteration":320,"passed_time":0.7368286387,"remaining_time":1.558587681},
{"learn":[0.2232988136],"iteration":321,"passed_time":0.7389148472,"remaining_time":1.555851759},
{"learn":[0.2228532805],"iteration":322,"passed_time":0.7408551875,"remaining_time":1.552814124},
{"learn":[0.2226336628],"iteration":323,"passed_time":0.7427144995,"remaining_time":1.549614203},
{"learn":[0.2224394524],"iteration":324,"passed_time":0.7450018974,"remaining_time":1.547311633},
{"learn":[0.2221831602],"iteration":325,"passed_time":0.7469838344,"remaining_time":1.544377621},
{"learn":[0.2220301225],"iteration":326,"passed_time":0.7488936437,"remaining_time":1.541300985},
{"learn":[0.22167462],"iteration":327,"passed_time":0.750964317,"remaining_time":1.53856104},
{"learn":[0.2215312001],"iteration":328,"passed_time":0.7531038002,"remaining_time":1.535965501},
{"learn":[0.2213303246],"iteration":329,"passed_time":0.7554275116,"remaining_time":1.533746766},
{"learn":[0.2210530174],"iteration":330,"passed_time":0.7574593747,"remaining_time":1.530937528},
{"learn":[0.2208164428],"iteration":331,"passed_time":0.7594013187,"remaining_time":1.527952051},
{"learn":[0.2205766853],"iteration":332,"passed_time":0.7613000223,"remaining_time":1.524886231},
{"learn":[0.2205590003],"iteration":333,"passed_time":0.7622303949,"remaining_time":1.519896536},
{"learn":[0.2204411617],"iteration":334,"passed_time":0.7641007225,"remaining_time":1.516796957},
{"learn":[0.2200945386],"iteration":335,"passed_time":0.7660040568,"remaining_time":1.513769922},
{"learn":[0.2198202999],"iteration":336,"passed_time":0.7679105233,"remaining_time":1.510755718},
{"learn":[0.2195425105],"iteration":337,"passed_time":0.7703124416,"remaining_time":1.508718451},
{"learn":[0.2192346859],"iteration":338,"passed_time":0.7729941602,"remaining_time":1.507224601},
{"learn":[0.2189032557],"iteration":339,"passed_time":0.775118834,"remaining_time":1.504642442},
{"learn":[0.2184662243],"iteration":340,"passed_time":0.777093865,"remaining_time":1.501773774},
{"learn":[0.2182485122],"iteration":341,"passed_time":0.779012595,"remaining_time":1.49880201},
{"learn":[0.2178378196],"iteration":342,"passed_time":0.7809088128,"remaining_time":1.495793265},
{"learn":[0.2173299375],"iteration":343,"passed_time":0.7829766996,"remaining_time":1.493118357},
{"learn":[0.2169731548],"iteration":344,"passed_time":0.7850174232,"remaining_time":1.490395398},
{"learn":[0.2167975202],"iteration":345,"passed_time":0.7869361132,"remaining_time":1.487445717},
{"learn":[0.2167300817],"iteration":346,"passed_time":0.7883344436,"remaining_time":1.483522743},
{"learn":[0.2163471019],"iteration":347,"passed_time":0.7902586564,"remaining_time":1.480599552},
{"learn":[0.2159540263],"iteration":348,"passed_time":0.7921518872,"remaining_time":1.477624294},
{"learn":[0.2155749591],"iteration":349,"passed_time":0.7940789266,"remaining_time":1.474718007},
{"learn":[0.2152137455],"iteration":350,"passed_time":0.7959819001,"remaining_time":1.471772801},
{"learn":[0.2150655299],"iteration":351,"passed_time":0.7979337972,"remaining_time":1.468923581},
{"learn":[0.2147464713],"iteration":352,"passed_time":0.7999961311,"remaining_time":1.466281861},
{"learn":[0.2145892341],"iteration":353,"passed_time":0.8019527994,"remaining_time":1.463450589},
{"learn":[0.2142088356],"iteration":354,"passed_time":0.8039045763,"remaining_time":1.460615357},
{"learn":[0.2141941215],"iteration":355,"passed_time":0.8048975244,"remaining_time":1.456050578},
{"learn":[0.2137647885],"iteration":356,"passed_time":0.8067725729,"remaining_time":1.453094578},
{"learn":[0.2134510602],"iteration":357,"passed_time":0.8086893485,"remaining_time":1.450219446},
{"learn":[0.2131243464],"iteration":358,"passed_time":0.8106393512,"remaining_time":1.447408981},
{"learn":[0.212984295],"iteration":359,"passed_time":0.8125629927,"remaining_time":1.444556432},
{"learn":[0.2126684496],"iteration":360,"passed_time":0.8144157194,"remaining_time":1.441583503},
{"learn":[0.2124931494],"iteration":361,"passed_time":0.8166436432,"remaining_time":1.439278023},
{"learn":[0.2122043389],"iteration":362,"passed_time":0.8188280709,"remaining_time":1.436896642},
{"learn":[0.2120679119],"iteration":363,"passed_time":0.8208317384,"remaining_time":1.43420051},
{"learn":[0.2119352471],"iteration":364,"passed_time":0.8227543675,"remaining_time":1.431367187},
{"learn":[0.2118235],"iteration":365,"passed_time":0.8246322526,"remaining_time":1.428461334},
{"learn":[0.2115668898],"iteration":366,"passed_time":0.8265160615,"remaining_time":1.4255713},
{"learn":[0.2114964104],"iteration":367,"passed_time":0.8281520945,"remaining_time":1.422261206},
{"learn":[0.2112273649],"iteration":368,"passed_time":0.8300309419,"remaining_time":1.419375405},
{"learn":[0.2109467325],"iteration":369,"passed_time":0.8320735499,"remaining_time":1.416773882},
{"learn":[0.2107594872],"iteration":370,"passed_time":0.834387659,"remaining_time":1.414635681},
{"learn":[0.2104087522],"iteration":371,"passed_time":0.8365770132,"remaining_time":1.412285925},
{"learn":[0.21022998],"iteration":372,"passed_time":0.8386002712,"remaining_time":1.409657829},
{"learn":[0.2100337573],"iteration":373,"passed_time":0.8404884102,"remaining_time":1.406806804},
{"learn":[0.2098538555],"iteration":374,"passed_time":0.8425230497,"remaining_time":1.404205083},
{"learn":[0.2097173209],"iteration":375,"passed_time":0.8444073598,"remaining_time":1.401356895},
{"learn":[0.209386135],"iteration":376,"passed_time":0.8463004402,"remaining_time":1.398528314},
{"learn":[0.2091477306],"iteration":377,"passed_time":0.8482464186,"remaining_time":1.395791726},
{"learn":[0.20882256],"iteration":378,"passed_time":0.8504038536,"remaining_time":1.393405786},
{"learn":[0.2085106955],"iteration":379,"passed_time":0.8523310884,"remaining_time":1.39064546},
{"learn":[0.2082311032],"iteration":380,"passed_time":0.8542957252,"remaining_time":1.387950273},
{"learn":[0.2081167693],"iteration":381,"passed_time":0.8562389322,"remaining_time":1.385224241},
{"learn":[0.2078110589],"iteration":382,"passed_time":0.8581296972,"remaining_time":1.382417815},
{"learn":[0.2074769597],"iteration":383,"passed_time":0.8600491991,"remaining_time":1.379662257},
{"learn":[0.2073524473],"iteration":384,"passed_time":0.8618965533,"remaining_time":1.376795793},
{"learn":[0.2070200305],"iteration":385,"passed_time":0.8641340042,"remaining_time":1.374555126},
{"learn":[0.2067411367],"iteration":386,"passed_time":0.8665095517,"remaining_time":1.372533218},
{"learn":[0.2064467363],"iteration":387,"passed_time":0.8685257484,"remaining_time":1.369942675},
{"learn":[0.2062013414],"iteration":388,"passed_time":0.8704434059,"remaining_time":1.367200311},
{"learn":[0.2059991478],"iteration":389,"passed_time":0.8723372281,"remaining_time":1.364424895},
{"learn":[0.2057228719],"iteration":390,"passed_time":0.8742236331,"remaining_time":1.361642436},
{"learn":[0.2055334638],"iteration":391,"passed_time":0.8761333221,"remaining_time":1.358900663},
{"learn":[0.2053152285],"iteration":392,"passed_time":0.8780350026,"remaining_time":1.356150755},
{"learn":[0.2049964162],"iteration":393,"passed_time":0.8800063745,"remaining_time":1.353512342},
{"learn":[0.2046588038],"iteration":394,"passed_time":0.8821469953,"remaining_time":1.351136537},
{"learn":[0.2043944937],"iteration":395,"passed_time":0.8840762298,"remaining_time":1.348439502},
{"learn":[0.2042239691],"iteration":396,"passed_time":0.8861110497,"remaining_time":1.345906708},
{"learn":[0.203978275],"iteration":397,"passed_time":0.8880326064,"remaining_time":1.343205098},
{"learn":[0.203835811],"iteration":398,"passed_time":0.8898519053,"remaining_time":1.340353371},
{"learn":[0.2037355443],"iteration":399,"passed_time":0.8917289886,"remaining_time":1.337593483},
{"learn":[0.2035324287],"iteration":400,"passed_time":0.8936428474,"remaining_time":1.334892932},
{"learn":[0.2033663334],"iteration":401,"passed_time":0.8955349054,"remaining_time":1.332163864},
{"learn":[0.2031232872],"iteration":402,"passed_time":0.8978376181,"remaining_time":1.33004729},
{"learn":[0.2029287752],"iteration":403,"passed_time":0.8997712528,"remaining_time":1.327385314},
{"learn":[0.2027215458],"iteration":404,"passed_time":0.9016702169,"remaining_time":1.324675998},
{"learn":[0.2024410166],"iteration":405,"passed_time":0.9035583759,"remaining_time":1.321954865},
{"learn":[0.2021318349],"iteration":406,"passed_time":0.905445272,"remaining_time":1.319235986},
{"learn":[0.2019515527],"iteration":407,"passed_time":0.907488306,"remaining_time":1.316747738},
{"learn":[0.2017063599],"iteration":408,"passed_time":0.9094264011,"remaining_time":1.314110032},
{"learn":[0.201521336],"iteration":409,"passed_time":0.9114780051,"remaining_time":1.31163908},
{"learn":[0.2010351959],"iteration":410,"passed_time":0.9138063673,"remaining_time":1.309566789},
{"learn":[0.200854024],"iteration":411,"passed_time":0.9159181712,"remaining_time":1.307184186},
{"learn":[0.2007086708],"iteration":412,"passed_time":0.9181857772,"remaining_time":1.305024337},
{"learn":[0.2004327402],"iteration":413,"passed_time":0.9204065085,"remaining_time":1.302797618},
{"learn":[0.2003182685],"iteration":414,"passed_time":0.9224903732,"remaining_time":1.300377996},
{"learn":[0.2000910197],"iteration":415,"passed_time":0.9244395842,"remaining_time":1.297770955},
{"learn":[0.1997597179],"iteration":416,"passed_time":0.9263733592,"remaining_time":1.295145488},
{"learn":[0.1994710391],"iteration":417,"passed_time":0.9283690081,"remaining_time":1.29260948},
{"learn":[0.1993394474],"iteration":418,"passed_time":0.9303906574,"remaining_time":1.290112105},
{"learn":[0.1990324566],"iteration":419,"passed_time":0.9323293339,"remaining_time":1.287502413},
{"learn":[0.1988854719],"iteration":420,"passed_time":0.934282269,"remaining_time":1.28491552},
{"learn":[0.1987799889],"iteration":421,"passed_time":0.9357370142,"remaining_time":1.281649275},
{"learn":[0.1984382624],"iteration":422,"passed_time":0.9376142377,"remaining_time":1.278967885},
{"learn":[0.198180043],"iteration":423,"passed_time":0.9395556305,"remaining_time":1.27637746},
{"learn":[0.1979572427],"iteration":424,"passed_time":0.9414535622,"remaining_time":1.27373129},
{"learn":[0.1978205254],"iteration":425,"passed_time":0.9433661881,"remaining_time":1.271108432},
{"learn":[0.1974619352],"iteration":426,"passed_time":0.9453602232,"remaining_time":1.268598145},
{"learn":[0.1972792365],"iteration":427,"passed_time":0.9473406868,"remaining_time":1.266072133},
{"learn":[0.1972627056],"iteration":428,"passed_time":0.948504518,"remaining_time":1.262461724},
{"learn":[0.1971656792],"iteration":429,"passed_time":0.9509902911,"remaining_time":1.260615037},
{"learn":[0.1969627589],"iteration":430,"passed_time":0.9536191619,"remaining_time":1.2589543},
{"learn":[0.1967971964],"iteration":431,"passed_time":0.9557690092,"remaining_time":1.256659253},
{"learn":[0.1964834802],"iteration":432,"passed_time":0.9577959057,"remaining_time":1.254203877},
{"learn":[0.1962809275],"iteration":433,"passed_time":0.9597357399,"remaining_time":1.251636933},
{"learn":[0.1960994002],"iteration":434,"passed_time":0.9619264923,"remaining_time":1.249398777},
{"learn":[0.1957143911],"iteration":435,"passed_time":0.9640032597,"remaining_time":1.247013391},
{"learn":[0.1956279211],"iteration":436,"passed_time":0.9660805083,"remaining_time":1.244630037},
{"learn":[0.1954779927],"iteration":437,"passed_time":0.9687769712,"remaining_time":1.243042598},
{"learn":[0.1952453966],"iteration":438,"passed_time":0.9708920677,"remaining_time":1.240707175},
{"learn":[0.1949740289],"iteration":439,"passed_time":0.9728506604,"remaining_time":1.238173568},
{"learn":[0.1947166975],"iteration":440,"passed_time":0.9747600789,"remaining_time":1.235580236},
{"learn":[0.194392402],"iteration":441,"passed_time":0.9768956329,"remaining_time":1.233275482},
{"learn":[0.1941507497],"iteration":442,"passed_time":0.97919594,"remaining_time":1.231178642},
{"learn":[0.1940110964],"iteration":443,"passed_time":0.9813397232,"remaining_time":1.228884879},
{"learn":[0.1938354423],"iteration":444,"passed_time":0.9835309523,"remaining_time":1.226650963},
{"learn":[0.1936193664],"iteration":445,"passed_time":0.9860530994,"remaining_time":1.224828289},
{"learn":[0.19348716],"iteration":446,"passed_time":0.9881705163,"remaining_time":1.22250178},
{"learn":[0.1933594562],"iteration":447,"passed_time":0.9902305649,"remaining_time":1.220105517},
{"learn":[0.1931857106],"iteration":448,"passed_time":0.9923535804,"remaining_time":1.217788024},
{"learn":[0.192977649],"iteration":449,"passed_time":0.9943967598,"remaining_time":1.215373817},
{"learn":[0.192831964],"iteration":450,"passed_time":0.9962493962,"remaining_time":1.212729309},
{"learn":[0.1925160072],"iteration":451,"passed_time":0.9985918212,"remaining_time":1.210682119},
{"learn":[0.192215778],"iteration":452,"passed_time":1.000679855,"remaining_time":1.208326447},
{"learn":[0.1921510981],"iteration":453,"passed_time":1.002942484,"remaining_time":1.20618193},
{"learn":[0.1920212097],"iteration":454,"passed_time":1.005228849,"remaining_time":1.204065324},
{"learn":[0.1917871208],"iteration":455,"passed_time":1.007204321,"remaining_time":1.201577085},
{"learn":[0.1915968468],"iteration":456,"passed_time":1.009295963,"remaining_time":1.19922912},
{"learn":[0.1915295566],"iteration":457,"passed_time":1.011237416,"remaining_time":1.19670454},
{"learn":[0.1913102263],"iteration":458,"passed_time":1.013538624,"remaining_time":1.194606527},
{"learn":[0.1912001667],"iteration":459,"passed_time":1.015841271,"remaining_time":1.192509318},
{"learn":[0.1909986995],"iteration":460,"passed_time":1.017866118,"remaining_time":1.190086415},
{"learn":[0.1908780175],"iteration":461,"passed_time":1.019833441,"remaining_time":1.187598249},
{"learn":[0.1907666674],"iteration":462,"passed_time":1.021748212,"remaining_time":1.185051382},
{"learn":[0.1905967805],"iteration":463,"passed_time":1.023801184,"remaining_time":1.182666885},
{"learn":[0.1903717437],"iteration":464,"passed_time":1.02612006,"remaining_time":1.180589747},
{"learn":[0.1901088826],"iteration":465,"passed_time":1.028470057,"remaining_time":1.178547233},
{"learn":[0.1898985418],"iteration":466,"passed_time":1.030621674,"remaining_time":1.176276986},
{"learn":[0.1897997368],"iteration":467,"passed_time":1.0325989,"remaining_time":1.173809006},
{"learn":[0.1896931164],"iteration":468,"passed_time":1.034507527,"remaining_time":1.171265452},
{"learn":[0.189558681],"iteration":469,"passed_time":1.036358209,"remaining_time":1.168659257},
{"learn":[0.1894170161],"iteration":470,"passed_time":1.038295091,"remaining_time":1.166153085},
{"learn":[0.1890971487],"iteration":471,"passed_time":1.040520103,"remaining_time":1.163971641},
{"learn":[0.1887453596],"iteration":472,"passed_time":1.042969201,"remaining_time":1.162039681},
{"learn":[0.1884247884],"iteration":473,"passed_time":1.045043994,"remaining_time":1.15969017},
{"learn":[0.1883093953],"iteration":474,"passed_time":1.047174797,"remaining_time":1.157403723},
{"learn":[0.1880066948],"iteration":475,"passed_time":1.049368807,"remaining_time":1.15518751},
{"learn":[0.1877244934],"iteration":476,"passed_time":1.051511357,"remaining_time":1.152914968},
{"learn":[0.1874979349],"iteration":477,"passed_time":1.053664062,"remaining_time":1.150654059},
{"learn":[0.1872680459],"iteration":478,"passed_time":1.056279211,"remaining_time":1.148896595},
{"learn":[0.1871071384],"iteration":479,"passed_time":1.058929411,"remaining_time":1.147173528},
{"learn":[0.186920616],"iteration":480,"passed_time":1.06150579,"remaining_time":1.145366954},
{"learn":[0.186763665],"iteration":481,"passed_time":1.063442722,"remaining_time":1.142869979},
{"learn":[0.1865379425],"iteration":482,"passed_time":1.065547679,"remaining_time":1.140555176},
{"learn":[0.1863773085],"iteration":483,"passed_time":1.067807533,"remaining_time":1.138406378},
{"learn":[0.186052941],"iteration":484,"passed_time":1.069935138,"remaining_time":1.136116693},
{"learn":[0.1858624703],"iteration":485,"passed_time":1.072171467,"remaining_time":1.133942662},
{"learn":[0.185679564],"iteration":486,"passed_time":1.074193316,"remaining_time":1.131542446},
{"learn":[0.1854023062],"iteration":487,"passed_time":1.076356645,"remaining_time":1.129292218},
{"learn":[0.185267539],"iteration":488,"passed_time":1.078344305,"remaining_time":1.126858773},
{"learn":[0.1849846116],"iteration":489,"passed_time":1.081271485,"remaining_time":1.125405015},
{"learn":[0.1847385884],"iteration":490,"passed_time":1.084658172,"remaining_time":1.124421608},
{"learn":[0.1845479304],"iteration":491,"passed_time":1.087280637,"remaining_time":1.122639357},
{"learn":[0.1842767841],"iteration":492,"passed_time":1.091927338,"remaining_time":1.122935417},
{"learn":[0.1840480833],"iteration":493,"passed_time":1.094769004,"remaining_time":1.121362583},
{"learn":[0.1838849528],"iteration":494,"passed_time":1.097676192,"remaining_time":1.119851469},
{"learn":[0.1836184184],"iteration":495,"passed_time":1.1004933,"remaining_time":1.118243192},
{"learn":[0.1835430521],"iteration":496,"passed_time":1.10444665,"remaining_time":1.11778001},
{"learn":[0.183370731],"iteration":497,"passed_time":1.108163505,"remaining_time":1.117064417},
{"learn":[0.1831741237],"iteration":498,"passed_time":1.110731319,"remaining_time":1.115183148},
{"learn":[0.1828442088],"iteration":499,"passed_time":1.11300343,"remaining_time":1.11300343},
{"learn":[0.1825912944],"iteration":500,"passed_time":1.115279336,"remaining_time":1.110827123},
{"learn":[0.1824519307],"iteration":501,"passed_time":1.117730568,"remaining_time":1.108824349},
{"learn":[0.1823191189],"iteration":502,"passed_time":1.120520222,"remaining_time":1.107154176},
{"learn":[0.1821918164],"iteration":503,"passed_time":1.123198589,"remaining_time":1.10537004},
{"learn":[0.1821145094],"iteration":504,"passed_time":1.125725522,"remaining_time":1.103433927},
{"learn":[0.1818610365],"iteration":505,"passed_time":1.128151307,"remaining_time":1.10139673},
{"learn":[0.1815223365],"iteration":506,"passed_time":1.13121988,"remaining_time":1.099983039},
{"learn":[0.1813070709],"iteration":507,"passed_time":1.134530856,"remaining_time":1.0987976},
{"learn":[0.181013523],"iteration":508,"passed_time":1.143322276,"remaining_time":1.102890447},
{"learn":[0.1808239604],"iteration":509,"passed_time":1.145771685,"remaining_time":1.100839462},
{"learn":[0.1805933849],"iteration":510,"passed_time":1.14797214,"remaining_time":1.098548682},
{"learn":[0.1804700304],"iteration":511,"passed_time":1.150147211,"remaining_time":1.09623406},
{"learn":[0.180220963],"iteration":512,"passed_time":1.152835109,"remaining_time":1.094406819},
{"learn":[0.1799494916],"iteration":513,"passed_time":1.15557168,"remaining_time":1.09262225},
{"learn":[0.1797561875],"iteration":514,"passed_time":1.157819179,"remaining_time":1.090373402},
{"learn":[0.179436986],"iteration":515,"passed_time":1.160004925,"remaining_time":1.088066635},
{"learn":[0.1792505404],"iteration":516,"passed_time":1.162139407,"remaining_time":1.085712444},
{"learn":[0.1790559559],"iteration":517,"passed_time":1.164270215,"remaining_time":1.083355682},
{"learn":[0.1788376129],"iteration":518,"passed_time":1.16652469,"remaining_time":1.081114404},
{"learn":[0.1785473959],"iteration":519,"passed_time":1.169119391,"remaining_time":1.079187131},
{"learn":[0.1783413345],"iteration":520,"passed_time":1.171508309,"remaining_time":1.0770681},
{"learn":[0.1782039539],"iteration":521,"passed_time":1.173646825,"remaining_time":1.07471874},
{"learn":[0.1780691309],"iteration":522,"passed_time":1.175960082,"remaining_time":1.072529558},
{"learn":[0.1778536814],"iteration":523,"passed_time":1.178247048,"remaining_time":1.070316021},
{"learn":[0.1775037336],"iteration":524,"passed_time":1.180590931,"remaining_time":1.0681537},
{"learn":[0.177240039],"iteration":525,"passed_time":1.18269834,"remaining_time":1.065777591},
{"learn":[0.1769428401],"iteration":526,"passed_time":1.18528388,"remaining_time":1.063831642},
{"learn":[0.1768412853],"iteration":527,"passed_time":1.187479218,"remaining_time":1.061534453},
{"learn":[0.1766448767],"iteration":528,"passed_time":1.189517601,"remaining_time":1.059097902},
{"learn":[0.1765102644],"iteration":529,"passed_time":1.191712669,"remaining_time":1.0568018},
{"learn":[0.1761971473],"iteration":530,"passed_time":1.193829644,"remaining_time":1.054437106},
{"learn":[0.1760432699],"iteration":531,"passed_time":1.195904703,"remaining_time":1.052036468},
{"learn":[0.1758868852],"iteration":532,"passed_time":1.198422416,"remaining_time":1.050024893},
{"learn":[0.1756532844],"iteration":533,"passed_time":1.200969847,"remaining_time":1.048037357},
{"learn":[0.1755397647],"iteration":534,"passed_time":1.203205032,"remaining_time":1.045776337},
{"learn":[0.1753129369],"iteration":535,"passed_time":1.205287734,"remaining_time":1.043383411},
{"learn":[0.1751058442],"iteration":536,"passed_time":1.207284796,"remaining_time":1.040917804},
{"learn":[0.1749863197],"iteration":537,"passed_time":1.20952565,"remaining_time":1.03866329},
{"learn":[0.1747661333],"iteration":538,"passed_time":1.211775414,"remaining_time":1.036416449},
{"learn":[0.1745895313],"iteration":539,"passed_time":1.213871266,"remaining_time":1.034038486},
{"learn":[0.1743996713],"iteration":540,"passed_time":1.216332642,"remaining_time":1.031971687},
{"learn":[0.174156363],"iteration":541,"passed_time":1.21840279,"remaining_time":1.029572837},
{"learn":[0.1739944455],"iteration":542,"passed_time":1.220430097,"remaining_time":1.027139142},
{"learn":[0.1736366776],"iteration":543,"passed_time":1.222376807,"remaining_time":1.024639382},
{"learn":[0.1735001575],"iteration":544,"passed_time":1.224361886,"remaining_time":1.022173685},
{"learn":[0.1732552725],"iteration":545,"passed_time":1.226508852,"remaining_time":1.019844357},
{"learn":[0.1730085494],"iteration":546,"passed_time":1.229006643,"remaining_time":1.017806233},
{"learn":[0.1726767117],"iteration":547,"passed_time":1.231369055,"remaining_time":1.015654768},
{"learn":[0.1725060816],"iteration":548,"passed_time":1.233491418,"remaining_time":1.013305336},
{"learn":[0.1723532143],"iteration":549,"passed_time":1.235822105,"remaining_time":1.011127177},
{"learn":[0.172166864],"iteration":550,"passed_time":1.238031481,"remaining_time":1.00884961},
{"learn":[0.1720073361],"iteration":551,"passed_time":1.240186871,"remaining_time":1.006528475},
{"learn":[0.1719256186],"iteration":552,"passed_time":1.242149322,"remaining_time":1.004051984},
{"learn":[0.1716307558],"iteration":553,"passed_time":1.244237988,"remaining_time":1.001678958},
{"learn":[0.1713701396],"iteration":554,"passed_time":1.246268664,"remaining_time":0.99926046},
{"learn":[0.1711539107],"iteration":555,"passed_time":1.248347351,"remaining_time":0.9968816972},
{"learn":[0.1709692119],"iteration":556,"passed_time":1.250504785,"remaining_time":0.9945666427},
{"learn":[0.1707621161],"iteration":557,"passed_time":1.252591936,"remaining_time":0.9921964799},
{"learn":[0.1705689116],"iteration":558,"passed_time":1.254672168,"remaining_time":0.9898218714},
{"learn":[0.1705014771],"iteration":559,"passed_time":1.256888023,"remaining_time":0.9875548754},
{"learn":[0.1703009596],"iteration":560,"passed_time":1.259006558,"remaining_time":0.9852119053},
{"learn":[0.1701639255],"iteration":561,"passed_time":1.261331432,"remaining_time":0.9830305466},
{"learn":[0.1699370426],"iteration":562,"passed_time":1.2634947,"remaining_time":0.98072324},
{"learn":[0.1698041076],"iteration":563,"passed_time":1.265864044,"remaining_time":0.9785757502},
{"learn":[0.1696493644],"iteration":564,"passed_time":1.268253889,"remaining_time":0.9764432597},
{"learn":[0.1692757807],"iteration":565,"passed_time":1.270437645,"remaining_time":0.9741518339},
{"learn":[0.1690649952],"iteration":566,"passed_time":1.272525373,"remaining_time":0.9717874542},
{"learn":[0.1688905388],"iteration":567,"passed_time":1.274665493,"remaining_time":0.9694638959},
{"learn":[0.1687465026],"iteration":568,"passed_time":1.27675331,"remaining_time":0.9671013649},
{"learn":[0.1685996475],"iteration":569,"passed_time":1.278867464,"remaining_time":0.9647596661},
{"learn":[0.1684645889],"iteration":570,"passed_time":1.281036352,"remaining_time":0.9624598864},
{"learn":[0.1682980472],"iteration":571,"passed_time":1.283097483,"remaining_time":0.9600799351},
{"learn":[0.168203478],"iteration":572,"passed_time":1.285286997,"remaining_time":0.9577967677},
{"learn":[0.1680254676],"iteration":573,"passed_time":1.287452658,"remaining_time":0.9554962234},
{"learn":[0.1678616057],"iteration":574,"passed_time":1.289506863,"remaining_time":0.9531137681},
{"learn":[0.1677539173],"iteration":575,"passed_time":1.291582942,"remaining_time":0.9507485547},
{"learn":[0.1676049358],"iteration":576,"passed_time":1.293737531,"remaining_time":0.9484418991},
{"learn":[0.1675024472],"iteration":577,"passed_time":1.296297462,"remaining_time":0.946431711},
{"learn":[0.1674397354],"iteration":578,"passed_time":1.298634519,"remaining_time":0.9442575694},
{"learn":[0.1672316596],"iteration":579,"passed_time":1.300958993,"remaining_time":0.9420737533},
{"learn":[0.1670614461],"iteration":580,"passed_time":1.303009804,"remaining_time":0.9396920961},
{"learn":[0.1668852431],"iteration":581,"passed_time":1.305120952,"remaining_time":0.9373549106},
{"learn":[0.166703729],"iteration":582,"passed_time":1.307126319,"remaining_time":0.9349428389},
{"learn":[0.1665781029],"iteration":583,"passed_time":1.309302452,"remaining_time":0.9326538014},
{"learn":[0.1664030877],"iteration":584,"passed_time":1.311715661,"remaining_time":0.9305333325},
{"learn":[0.1662446916],"iteration":585,"passed_time":1.314208466,"remaining_time":0.9284680971},
{"learn":[0.1661797747],"iteration":586,"passed_time":1.316263358,"remaining_time":0.9260932993},
{"learn":[0.1659553802],"iteration":587,"passed_time":1.318343483,"remaining_time":0.9237372702},
{"learn":[0.1657916099],"iteration":588,"passed_time":1.320502366,"remaining_time":0.9214371349},
{"learn":[0.1657077064],"iteration":589,"passed_time":1.32280978,"remaining_time":0.9192406943},
{"learn":[0.1656156629],"iteration":590,"passed_time":1.325036466,"remaining_time":0.9169880109},
{"learn":[0.1654051306],"iteration":591,"passed_time":1.328020793,"remaining_time":0.9152575733},
{"learn":[0.1651401876],"iteration":592,"passed_time":1.331101789,"remaining_time":0.9135892551},
{"learn":[0.1649081792],"iteration":593,"passed_time":1.333697518,"remaining_time":0.9115844989},
{"learn":[0.1647325813],"iteration":594,"passed_time":1.335920485,"remaining_time":0.9093240279},
{"learn":[0.16457753],"iteration":595,"passed_time":1.338036569,"remaining_time":0.9069912315},
{"learn":[0.1643842641],"iteration":596,"passed_time":1.340018391,"remaining_time":0.9045685286},
{"learn":[0.1642680262],"iteration":597,"passed_time":1.342071839,"remaining_time":0.9021954504},
{"learn":[0.1640650437],"iteration":598,"passed_time":1.344383648,"remaining_time":0.8999963987},
{"learn":[0.163950623],"iteration":599,"passed_time":1.346857403,"remaining_time":0.8979049355},
{"learn":[0.1639297583],"iteration":600,"passed_time":1.348478331,"remaining_time":0.8952460135},
{"learn":[0.1637489118],"iteration":601,"passed_time":1.350619357,"remaining_time":0.8929343922},
{"learn":[0.163553794],"iteration":602,"passed_time":1.352678229,"remaining_time":0.8905692484},
{"learn":[0.163537428],"iteration":603,"passed_time":1.353987442,"remaining_time":0.8877136209},
{"learn":[0.1633687361],"iteration":604,"passed_time":1.355921351,"remaining_time":0.885270965},
{"learn":[0.1631926108],"iteration":605,"passed_time":1.358040694,"remaining_time":0.88295055},
{"learn":[0.1629418003],"iteration":606,"passed_time":1.36037076,"remaining_time":0.8807672304},
{"learn":[0.1628737067],"iteration":607,"passed_time":1.362443944,"remaining_time":0.878417806},
{"learn":[0.1627259063],"iteration":608,"passed_time":1.364377519,"remaining_time":0.8759796548},
{"learn":[0.1624496201],"iteration":609,"passed_time":1.366360242,"remaining_time":0.8735745812},
{"learn":[0.1622320799],"iteration":610,"passed_time":1.368406119,"remaining_time":0.8712110968},
{"learn":[0.162118661],"iteration":611,"passed_time":1.370389793,"remaining_time":0.8688092153},
{"learn":[0.1619028684],"iteration":612,"passed_time":1.372393421,"remaining_time":0.866421295},
{"learn":[0.1617321161],"iteration":613,"passed_time":1.374566723,"remaining_time":0.8641412951},
{"learn":[0.161579612],"iteration":614,"passed_time":1.377060229,"remaining_time":0.8620620949},
{"learn":[0.1614310089],"iteration":615,"passed_time":1.379077178,"remaining_time":0.8596844745},
{"learn":[0.1613019316],"iteration":616,"passed_time":1.38114728,"remaining_time":0.8573410181},
{"learn":[0.1611456177],"iteration":617,"passed_time":1.383134028,"remaining_time":0.8549469235},
{"learn":[0.1610482985],"iteration":618,"passed_time":1.385099071,"remaining_time":0.8525407851},
{"learn":[0.1609868779],"iteration":619,"passed_time":1.387250697,"remaining_time":0.8502504273},
{"learn":[0.1607575817],"iteration":620,"passed_time":1.389263601,"remaining_time":0.8478758532},
{"learn":[0.1606159918],"iteration":621,"passed_time":1.391878364,"remaining_time":0.845868202},
{"learn":[0.1604256137],"iteration":622,"passed_time":1.394224673,"remaining_time":0.8436961505},
{"learn":[0.1601647371],"iteration":623,"passed_time":1.396477184,"remaining_time":0.8414670212},
{"learn":[0.1600875781],"iteration":624,"passed_time":1.398498573,"remaining_time":0.8390991437},
{"learn":[0.1598537074],"iteration":625,"passed_time":1.400690438,"remaining_time":0.8368342232},
{"learn":[0.1596711789],"iteration":626,"passed_time":1.402947254,"remaining_time":0.8346081749},
{"learn":[0.1594671884],"iteration":627,"passed_time":1.405095608,"remaining_time":0.8323177803},
{"learn":[0.1592592756],"iteration":628,"passed_time":1.407543713,"remaining_time":0.8302046385},
{"learn":[0.1591275275],"iteration":629,"passed_time":1.409891586,"remaining_time":0.8280315663},
{"learn":[0.158845801],"iteration":630,"passed_time":1.412226468,"remaining_time":0.8258503435},
{"learn":[0.1587100076],"iteration":631,"passed_time":1.41444046,"remaining_time":0.8235982423},
{"learn":[0.1586098873],"iteration":632,"passed_time":1.41665629,"remaining_time":0.8213473279},
{"learn":[0.1584537829],"iteration":633,"passed_time":1.4188414,"remaining_time":0.819078789},
{"learn":[0.1581235482],"iteration":634,"passed_time":1.420962781,"remaining_time":0.8167738818},
{"learn":[0.1579744256],"iteration":635,"passed_time":1.423298069,"remaining_time":0.8145919766},
{"learn":[0.1578194197],"iteration":636,"passed_time":1.4255206,"remaining_time":0.8123453343},
{"learn":[0.1577738517],"iteration":637,"passed_time":1.427499786,"remaining_time":0.8099606936},
{"learn":[0.1575649928],"iteration":638,"passed_time":1.429670031,"remaining_time":0.8076852599},
{"learn":[0.1573649575],"iteration":639,"passed_time":1.431875021,"remaining_time":0.8054296994},
{"learn":[0.1572679447],"iteration":640,"passed_time":1.433886081,"remaining_time":0.8030656833},
{"learn":[0.1571941444],"iteration":641,"passed_time":1.436048207,"remaining_time":0.8007870062},
{"learn":[0.1569755928],"iteration":642,"passed_time":1.438316138,"remaining_time":0.7985674361},
{"learn":[0.1568179924],"iteration":643,"passed_time":1.440607294,"remaining_time":0.796360554},
{"learn":[0.1566645105],"iteration":644,"passed_time":1.443261504,"remaining_time":0.7943532309},
{"learn":[0.1564860056],"iteration":645,"passed_time":1.445517202,"remaining_time":0.7921255257},
{"learn":[0.1563753724],"iteration":646,"passed_time":1.447600039,"remaining_time":0.7898034215},
{"learn":[0.1562509833],"iteration":647,"passed_time":1.449790581,"remaining_time":0.7875405624},
{"learn":[0.1561351735],"iteration":648,"passed_time":1.451849276,"remaining_time":0.7852066193},
{"learn":[0.1558858579],"iteration":649,"passed_time":1.453970687,"remaining_time":0.7829072932},
{"learn":[0.1557147765],"iteration":650,"passed_time":1.456896333,"remaining_time":0.7810396624},
{"learn":[0.1555652674],"iteration":651,"passed_time":1.459188425,"remaining_time":0.7788306318},
{"learn":[0.155483305],"iteration":652,"passed_time":1.461189958,"remaining_time":0.7764669454},
{"learn":[0.1552871692],"iteration":653,"passed_time":1.463192316,"remaining_time":0.7741048032},
{"learn":[0.1551693364],"iteration":654,"passed_time":1.465320353,"remaining_time":0.771809957},
{"learn":[0.1549616616],"iteration":655,"passed_time":1.467496086,"remaining_time":0.7695406303},
{"learn":[0.1547867003],"iteration":656,"passed_time":1.469573184,"remaining_time":0.7672200945},
{"learn":[0.1546067616],"iteration":657,"passed_time":1.47206237,"remaining_time":0.7651144841},
{"learn":[0.1543712035],"iteration":658,"passed_time":1.47444787,"remaining_time":0.7629540572},
{"learn":[0.1542317179],"iteration":659,"passed_time":1.476706926,"remaining_time":0.7607278105},
{"learn":[0.154056191],"iteration":660,"passed_time":1.478829044,"remaining_time":0.7584312344},
{"learn":[0.1537784471],"iteration":661,"passed_time":1.480977779,"remaining_time":0.7561487753},
{"learn":[0.1535598906],"iteration":662,"passed_time":1.483049931,"remaining_time":0.7538277927},
{"learn":[0.1534205765],"iteration":663,"passed_time":1.485197733,"remaining_time":0.7515458408},
{"learn":[0.1533696489],"iteration":664,"passed_time":1.487731904,"remaining_time":0.749458929},
{"learn":[0.153139882],"iteration":665,"passed_time":1.490172537,"remaining_time":0.7473237648},
{"learn":[0.152915017],"iteration":666,"passed_time":1.492523782,"remaining_time":0.7451430578},
{"learn":[0.1528584399],"iteration":667,"passed_time":1.494626796,"remaining_time":0.7428384674},
{"learn":[0.1526857963],"iteration":668,"passed_time":1.496670321,"remaining_time":0.7405050467},
{"learn":[0.1525842482],"iteration":669,"passed_time":1.498671282,"remaining_time":0.7381515271},
{"learn":[0.1524482656],"iteration":670,"passed_time":1.50076115,"remaining_time":0.7358426504},
{"learn":[0.1522128187],"iteration":671,"passed_time":1.503027839,"remaining_time":0.733620731},
{"learn":[0.1519530408],"iteration":672,"passed_time":1.50526915,"remaining_time":0.7313863475},
{"learn":[0.1518505257],"iteration":673,"passed_time":1.507301493,"remaining_time":0.7290508706},
{"learn":[0.1516769591],"iteration":674,"passed_time":1.509623069,"remaining_time":0.7268555516},
{"learn":[0.1515568618],"iteration":675,"passed_time":1.511595203,"remaining_time":0.7244923754},
{"learn":[0.1513558091],"iteration":676,"passed_time":1.513723346,"remaining_time":0.7222047871},
{"learn":[0.1511802394],"iteration":677,"passed_time":1.515858018,"remaining_time":0.7199207697},
{"learn":[0.1510348933],"iteration":678,"passed_time":1.517840701,"remaining_time":0.7175653386},
{"learn":[0.1509594734],"iteration":679,"passed_time":1.520037206,"remaining_time":0.7153116265},
{"learn":[0.1506919493],"iteration":680,"passed_time":1.522672167,"remaining_time":0.7132634674},
{"learn":[0.1505709008],"iteration":681,"passed_time":1.524961038,"remaining_time":0.711052214},
{"learn":[0.1503920482],"iteration":682,"passed_time":1.527174052,"remaining_time":0.7088055262},
{"learn":[0.1502623782],"iteration":683,"passed_time":1.529393606,"remaining_time":0.7065619584},
{"learn":[0.1501284477],"iteration":684,"passed_time":1.531580615,"remaining_time":0.7043034944},
{"learn":[0.1499893322],"iteration":685,"passed_time":1.533592998,"remaining_time":0.7019653079},
{"learn":[0.1499106404],"iteration":686,"passed_time":1.535756667,"remaining_time":0.6996969968},
{"learn":[0.1497735995],"iteration":687,"passed_time":1.538138343,"remaining_time":0.6975278533},
{"learn":[0.149597897],"iteration":688,"passed_time":1.540312231,"remaining_time":0.6952643018},
{"learn":[0.1494177518],"iteration":689,"passed_time":1.54257448,"remaining_time":0.6930407084},
{"learn":[0.1492597754],"iteration":690,"passed_time":1.544660409,"remaining_time":0.690738157},
{"learn":[0.1490293359],"iteration":691,"passed_time":1.546763588,"remaining_time":0.6884439089},
{"learn":[0.1488832832],"iteration":692,"passed_time":1.548968222,"remaining_time":0.6861951576},
{"learn":[0.1487187482],"iteration":693,"passed_time":1.551421159,"remaining_time":0.6840560154},
{"learn":[0.1485974324],"iteration":694,"passed_time":1.553955881,"remaining_time":0.6819518614},
{"learn":[0.1484730429],"iteration":695,"passed_time":1.556263375,"remaining_time":0.6797472211},
{"learn":[0.148327343],"iteration":696,"passed_time":1.55860604,"remaining_time":0.6775575756},
{"learn":[0.1481704796],"iteration":697,"passed_time":1.560925081,"remaining_time":0.6753572699},
{"learn":[0.148074985],"iteration":698,"passed_time":1.563298879,"remaining_time":0.6731802039},
{"learn":[0.1478117613],"iteration":699,"passed_time":1.565597552,"remaining_time":0.6709703794},
{"learn":[0.1476115813],"iteration":700,"passed_time":1.568280864,"remaining_time":0.668924363},
{"learn":[0.1474802751],"iteration":701,"passed_time":1.57048798,"remaining_time":0.6666743846},
{"learn":[0.1473228601],"iteration":702,"passed_time":1.57261539,"remaining_time":0.6643908546},
{"learn":[0.1471887233],"iteration":703,"passed_time":1.574762797,"remaining_time":0.6621161758},
{"learn":[0.1470337319],"iteration":704,"passed_time":1.576788265,"remaining_time":0.6597908342},
{"learn":[0.146917363],"iteration":705,"passed_time":1.578883058,"remaining_time":0.6574952112},
{"learn":[0.1466825765],"iteration":706,"passed_time":1.580919222,"remaining_time":0.6551758587},
{"learn":[0.1465704568],"iteration":707,"passed_time":1.583417354,"remaining_time":0.6530478353},
{"learn":[0.1464209218],"iteration":708,"passed_time":1.585844932,"remaining_time":0.6508898098},
{"learn":[0.1462853714],"iteration":709,"passed_time":1.588042941,"remaining_time":0.6486372576},
{"learn":[0.1461789579],"iteration":710,"passed_time":1.590420027,"remaining_time":0.646457648},
{"learn":[0.1460081602],"iteration":711,"passed_time":1.592485257,"remaining_time":0.64415134},
{"learn":[0.1459323555],"iteration":712,"passed_time":1.594669038,"remaining_time":0.6418934278},
{"learn":[0.1457609128],"iteration":713,"passed_time":1.596799656,"remaining_time":0.6396144281},
{"learn":[0.1455538608],"iteration":714,"passed_time":1.599237993,"remaining_time":0.6374585008},
{"learn":[0.1454027367],"iteration":715,"passed_time":1.601249589,"remaining_time":0.6351325186},
{"learn":[0.1452141273],"iteration":716,"passed_time":1.603372333,"remaining_time":0.6328512836},
{"learn":[0.1450399299],"iteration":717,"passed_time":1.605919319,"remaining_time":0.6307371141},
{"learn":[0.1449028202],"iteration":718,"passed_time":1.608161867,"remaining_time":0.6285027601},
{"learn":[0.1447656444],"iteration":719,"passed_time":1.610241867,"remaining_time":0.6262051703},
{"learn":[0.1446255346],"iteration":720,"passed_time":1.612410548,"remaining_time":0.6239425004},
{"learn":[0.1445407131],"iteration":721,"passed_time":1.614752296,"remaining_time":0.6217467289},
{"learn":[0.1442681237],"iteration":722,"passed_time":1.617350576,"remaining_time":0.6196488374},
{"learn":[0.1442140336],"iteration":723,"passed_time":1.619536246,"remaining_time":0.6173922707},
{"learn":[0.1439870918],"iteration":724,"passed_time":1.62175821,"remaining_time":0.615149666},
{"learn":[0.1438060957],"iteration":725,"passed_time":1.62400752,"remaining_time":0.6129174386},
{"learn":[0.1436657523],"iteration":726,"passed_time":1.626215332,"remaining_time":0.6106695813},
{"learn":[0.1435372925],"iteration":727,"passed_time":1.628225063,"remaining_time":0.6083478259},
{"learn":[0.1434194126],"iteration":728,"passed_time":1.630732582,"remaining_time":0.606211975},
{"learn":[0.1433528374],"iteration":729,"passed_time":1.632946964,"remaining_time":0.6039666855},
{"learn":[0.1432107624],"iteration":730,"passed_time":1.635084458,"remaining_time":0.6016931863},
{"learn":[0.1430376755],"iteration":731,"passed_time":1.63721052,"remaining_time":0.5994158735},
{"learn":[0.1428779645],"iteration":732,"passed_time":1.639518605,"remaining_time":0.5972052764},
{"learn":[0.1427728245],"iteration":733,"passed_time":1.64179216,"remaining_time":0.5949819},
{"learn":[0.1426738154],"iteration":734,"passed_time":1.643909427,"remaining_time":0.5927020382},
{"learn":[0.142521294],"iteration":735,"passed_time":1.646142943,"remaining_time":0.5904643167},
{"learn":[0.1424012457],"iteration":736,"passed_time":1.648441251,"remaining_time":0.5882497274},
{"learn":[0.1422380908],"iteration":737,"passed_time":1.650561353,"remaining_time":0.5859716457},
{"learn":[0.1420684661],"iteration":738,"passed_time":1.652679072,"remaining_time":0.58369315},
{"learn":[0.1419608682],"iteration":739,"passed_time":1.654847949,"remaining_time":0.5814330631},
{"learn":[0.141797423],"iteration":740,"passed_time":1.657047667,"remaining_time":0.5791840023},
{"learn":[0.1416498421],"iteration":741,"passed_time":1.659132653,"remaining_time":0.5768951811},
{"learn":[0.1415804089],"iteration":742,"passed_time":1.661401858,"remaining_time":0.5746706293},
{"learn":[0.1413794151],"iteration":743,"passed_time":1.664166765,"remaining_time":0.5726165214},
{"learn":[0.1412481196],"iteration":744,"passed_time":1.666529968,"remaining_time":0.5704230093},
{"learn":[0.1409958414],"iteration":745,"passed_time":1.668992493,"remaining_time":0.5682628594},
{"learn":[0.1407739532],"iteration":746,"passed_time":1.671294063,"remaining_time":0.5660473867},
{"learn":[0.1407240532],"iteration":747,"passed_time":1.673431681,"remaining_time":0.5637764488},
{"learn":[0.1404619035],"iteration":748,"passed_time":1.675586139,"remaining_time":0.56151151},
{"learn":[0.1403434937],"iteration":749,"passed_time":1.67816982,"remaining_time":0.5593899401},
{"learn":[0.1401468613],"iteration":750,"passed_time":1.680386282,"remaining_time":0.5571453852},
{"learn":[0.1400690965],"iteration":751,"passed_time":1.682398945,"remaining_time":0.5548336946},
{"learn":[0.1398869405],"iteration":752,"passed_time":1.684484994,"remaining_time":0.5525468705},
{"learn":[0.1397245433],"iteration":753,"passed_time":1.686735707,"remaining_time":0.5503143021},
{"learn":[0.1396100521],"iteration":754,"passed_time":1.688789861,"remaining_time":0.5480179021},
{"learn":[0.1394454038],"iteration":755,"passed_time":1.690899651,"remaining_time":0.5457400989},
{"learn":[0.1393416663],"iteration":756,"passed_time":1.693126211,"remaining_time":0.5435002237},
{"learn":[0.1392098179],"iteration":757,"passed_time":1.695475738,"remaining_time":0.5412996419},
{"learn":[0.1391092903],"iteration":758,"passed_time":1.697518256,"remaining_time":0.5390011854},
{"learn":[0.1388863],"iteration":759,"passed_time":1.699641416,"remaining_time":0.5367288682},
{"learn":[0.1387610606],"iteration":760,"passed_time":1.701661096,"remaining_time":0.5344244439},
{"learn":[0.1385174006],"iteration":761,"passed_time":1.703670526,"remaining_time":0.532117566},
{"learn":[0.1383332447],"iteration":762,"passed_time":1.705760249,"remaining_time":0.5298364076},
{"learn":[0.1381930724],"iteration":763,"passed_time":1.708080753,"remaining_time":0.5276270389},
{"learn":[0.1381191687],"iteration":764,"passed_time":1.710870267,"remaining_time":0.5255614546},
{"learn":[0.1379856585],"iteration":765,"passed_time":1.713081342,"remaining_time":0.5233172768},
{"learn":[0.1378145855],"iteration":766,"passed_time":1.715136394,"remaining_time":0.5210257885},
{"learn":[0.1376981773],"iteration":767,"passed_time":1.717359562,"remaining_time":0.5187857009},
{"learn":[0.1375592599],"iteration":768,"passed_time":1.719480792,"remaining_time":0.5165150362},
{"learn":[0.1373785825],"iteration":769,"passed_time":1.721505394,"remaining_time":0.5142158968},
{"learn":[0.1372346367],"iteration":770,"passed_time":1.723584251,"remaining_time":0.5119335842},
{"learn":[0.1371580261],"iteration":771,"passed_time":1.7256463,"remaining_time":0.5096468346},
{"learn":[0.136939713],"iteration":772,"passed_time":1.727749388,"remaining_time":0.507372718},
{"learn":[0.1368860302],"iteration":773,"passed_time":1.729691763,"remaining_time":0.5050521169},
{"learn":[0.136740148],"iteration":774,"passed_time":1.73182011,"remaining_time":0.5027864836},
{"learn":[0.1365702188],"iteration":775,"passed_time":1.733813569,"remaining_time":0.5004822673},
{"learn":[0.1363803735],"iteration":776,"passed_time":1.735831344,"remaining_time":0.4981858298},
{"learn":[0.1362213264],"iteration":777,"passed_time":1.737936107,"remaining_time":0.4959149302},
{"learn":[0.1360884841],"iteration":778,"passed_time":1.740049874,"remaining_time":0.4936470118},
{"learn":[0.1359397093],"iteration":779,"passed_time":1.742292828,"remaining_time":0.4914159258},
{"learn":[0.1358569475],"iteration":780,"passed_time":1.744275413,"remaining_time":0.4891117995},
{"learn":[0.1357789936],"iteration":781,"passed_time":1.746281556,"remaining_time":0.4868150628},
{"learn":[0.1355607971],"iteration":782,"passed_time":1.748520094,"remaining_time":0.4845834743},
{"learn":[0.1353266743],"iteration":783,"passed_time":1.750778078,"remaining_time":0.4823572255},
{"learn":[0.1352425682],"iteration":784,"passed_time":1.753081788,"remaining_time":0.4801434195},
{"learn":[0.1351280408],"iteration":785,"passed_time":1.7551949,"remaining_time":0.4778774917},
{"learn":[0.1350505557],"iteration":786,"passed_time":1.757666936,"remaining_time":0.4757090944},
{"learn":[0.1349975292],"iteration":787,"passed_time":1.760179561,"remaining_time":0.4735508465},
{"learn":[0.1348539293],"iteration":788,"passed_time":1.762748247,"remaining_time":0.4714066922},
{"learn":[0.1347369608],"iteration":789,"passed_time":1.765008982,"remaining_time":0.4691796029},
{"learn":[0.134663413],"iteration":790,"passed_time":1.767158303,"remaining_time":0.4669229904},
{"learn":[0.134591624],"iteration":791,"passed_time":1.76917004,"remaining_time":0.4646305155},
{"learn":[0.1345364543],"iteration":792,"passed_time":1.771152602,"remaining_time":0.4623311333},
{"learn":[0.1343585092],"iteration":793,"passed_time":1.773623532,"remaining_time":0.4601592538},
{"learn":[0.1341047241],"iteration":794,"passed_time":1.776051941,"remaining_time":0.4579756577},
{"learn":[0.1339294175],"iteration":795,"passed_time":1.77815499,"remaining_time":0.4557080628},
{"learn":[0.1337917544],"iteration":796,"passed_time":1.780338842,"remaining_time":0.4534614615},
{"learn":[0.1337244006],"iteration":797,"passed_time":1.782304591,"remaining_time":0.4511598087},
{"learn":[0.1335989343],"iteration":798,"passed_time":1.784578421,"remaining_time":0.448936499},
{"learn":[0.1335212192],"iteration":799,"passed_time":1.78672654,"remaining_time":0.4466816349},
{"learn":[0.1334495076],"iteration":800,"passed_time":1.788948464,"remaining_time":0.4444453736},
{"learn":[0.1332513047],"iteration":801,"passed_time":1.791557539,"remaining_time":0.4423047292},
{"learn":[0.1331554256],"iteration":802,"passed_time":1.793629571,"remaining_time":0.4400311649},
{"learn":[0.1330061518],"iteration":803,"passed_time":1.795596613,"remaining_time":0.4377325077},
{"learn":[0.1328546666],"iteration":804,"passed_time":1.797488671,"remaining_time":0.4354165104},
{"learn":[0.1327977903],"iteration":805,"passed_time":1.799463161,"remaining_time":0.4331214061},
{"learn":[0.1326536966],"iteration":806,"passed_time":1.801424651,"remaining_time":0.4308239871},
{"learn":[0.1324994083],"iteration":807,"passed_time":1.803380487,"remaining_time":0.4285260564},
{"learn":[0.1323868249],"iteration":808,"passed_time":1.805399484,"remaining_time":0.4262438831},
{"learn":[0.1321830912],"iteration":809,"passed_time":1.807367669,"remaining_time":0.4239504409},
{"learn":[0.13205341],"iteration":810,"passed_time":1.809253032,"remaining_time":0.4216384993},
{"learn":[0.1319533813],"iteration":811,"passed_time":1.811445008,"remaining_time":0.4193985978},
{"learn":[0.1318103766],"iteration":812,"passed_time":1.813539556,"remaining_time":0.4171364047},
{"learn":[0.1316615507],"iteration":813,"passed_time":1.815510157,"remaining_time":0.4148463012},
{"learn":[0.1315202342],"iteration":814,"passed_time":1.817584429,"remaining_time":0.4125805145},
{"learn":[0.1314476714],"iteration":815,"passed_time":1.820086394,"remaining_time":0.410411638},
{"learn":[0.1313666283],"iteration":816,"passed_time":1.822494672,"remaining_time":0.4082209607},
{"learn":[0.1312738161],"iteration":817,"passed_time":1.824486763,"remaining_time":0.4059371527},
{"learn":[0.1311778196],"iteration":818,"passed_time":1.826508959,"remaining_time":0.40366071},
{"learn":[0.1310555525],"iteration":819,"passed_time":1.828467061,"remaining_time":0.4013708182},
{"learn":[0.1308061637],"iteration":820,"passed_time":1.830495335,"remaining_time":0.3990970341},
{"learn":[0.130620853],"iteration":821,"passed_time":1.832521335,"remaining_time":0.3968233548},
{"learn":[0.1305884154],"iteration":822,"passed_time":1.83448509,"remaining_time":0.3945368905},
{"learn":[0.1304315769],"iteration":823,"passed_time":1.836770086,"remaining_time":0.3923198241},
{"learn":[0.1302849534],"iteration":824,"passed_time":1.839500382,"remaining_time":0.3901970508},
{"learn":[0.1301510832],"iteration":825,"passed_time":1.841632307,"remaining_time":0.3879467572},
{"learn":[0.1300290802],"iteration":826,"passed_time":1.843836617,"remaining_time":0.385711892},
{"learn":[0.1299597576],"iteration":827,"passed_time":1.845951929,"remaining_time":0.3834586132},
{"learn":[0.1297962542],"iteration":828,"passed_time":1.848021274,"remaining_time":0.3811961856},
{"learn":[0.129647064],"iteration":829,"passed_time":1.850298828,"remaining_time":0.3789768684},
{"learn":[0.1295345802],"iteration":830,"passed_time":1.852462743,"remaining_time":0.3767343003},
{"learn":[0.1293133811],"iteration":831,"passed_time":1.854757051,"remaining_time":0.3745182507},
{"learn":[0.1292086386],"iteration":832,"passed_time":1.85740671,"remaining_time":0.372373254},
{"learn":[0.1291147628],"iteration":833,"passed_time":1.859657352,"remaining_time":0.3701476264},
{"learn":[0.1289525201],"iteration":834,"passed_time":1.861707352,"remaining_time":0.3678822911},
{"learn":[0.1288493655],"iteration":835,"passed_time":1.863739361,"remaining_time":0.3656139415},
{"learn":[0.128730476],"iteration":836,"passed_time":1.865758068,"remaining_time":0.3633435664},
{"learn":[0.1285284824],"iteration":837,"passed_time":1.867777468,"remaining_time":0.3610739257},
{"learn":[0.1282962136],"iteration":838,"passed_time":1.870117266,"remaining_time":0.3588663645},
{"learn":[0.1281592316],"iteration":839,"passed_time":1.872193928,"remaining_time":0.3566083673},
{"learn":[0.1280631297],"iteration":840,"passed_time":1.874203154,"remaining_time":0.3543380518},
{"learn":[0.1279170149],"iteration":841,"passed_time":1.876263498,"remaining_time":0.3520779485},
{"learn":[0.1277495832],"iteration":842,"passed_time":1.878261128,"remaining_time":0.3498066394},
{"learn":[0.1276297904],"iteration":843,"passed_time":1.880265361,"remaining_time":0.3475371994},
{"learn":[0.1275578989],"iteration":844,"passed_time":1.882292919,"remaining_time":0.3452726656},
{"learn":[0.127389244],"iteration":845,"passed_time":1.884735321,"remaining_time":0.3430842074},
{"learn":[0.1272140967],"iteration":846,"passed_time":1.887033904,"remaining_time":0.3408691703},
{"learn":[0.1270889602],"iteration":847,"passed_time":1.888995008,"remaining_time":0.3385934449},
{"learn":[0.1268956967],"iteration":848,"passed_time":1.891005476,"remaining_time":0.3363272402},
{"learn":[0.1267265363],"iteration":849,"passed_time":1.893078229,"remaining_time":0.3340726287},
{"learn":[0.1266101756],"iteration":850,"passed_time":1.895263654,"remaining_time":0.3318381722},
{"learn":[0.1264654748],"iteration":851,"passed_time":1.897441316,"remaining_time":0.3296024822},
{"learn":[0.1264138391],"iteration":852,"passed_time":1.899642849,"remaining_time":0.3273710419},
{"learn":[0.1262976788],"iteration":853,"passed_time":1.90226991,"remaining_time":0.3252124203},
{"learn":[0.1262038362],"iteration":854,"passed_time":1.904715801,"remaining_time":0.323021978},
{"learn":[0.1260917252],"iteration":855,"passed_time":1.906957121,"remaining_time":0.320796525},
{"learn":[0.1259414929],"iteration":856,"passed_time":1.909061302,"remaining_time":0.3185481519},
{"learn":[0.1258475107],"iteration":857,"passed_time":1.911193338,"remaining_time":0.3163047249},
{"learn":[0.1257702651],"iteration":858,"passed_time":1.913307948,"remaining_time":0.314058697},
{"learn":[0.1256277477],"iteration":859,"passed_time":1.915572903,"remaining_time":0.3118374493},
{"learn":[0.1255272547],"iteration":860,"passed_time":1.917998055,"remaining_time":0.3096419625},
{"learn":[0.1253557742],"iteration":861,"passed_time":1.920165118,"remaining_time":0.3074046244},
{"learn":[0.1251778095],"iteration":862,"passed_time":1.922297174,"remaining_time":0.305161892},
{"learn":[0.1250412262],"iteration":863,"passed_time":1.924316673,"remaining_time":0.3029016985},
{"learn":[0.1248714982],"iteration":864,"passed_time":1.926335625,"remaining_time":0.3006419762},
{"learn":[0.1247988944],"iteration":865,"passed_time":1.928405697,"remaining_time":0.2983907199},
{"learn":[0.1247360856],"iteration":866,"passed_time":1.930465685,"remaining_time":0.2961383347},
{"learn":[0.1246745717],"iteration":867,"passed_time":1.933004277,"remaining_time":0.2939591758},
{"learn":[0.1245987796],"iteration":868,"passed_time":1.935196062,"remaining_time":0.2917269092},
{"learn":[0.1244699805],"iteration":869,"passed_time":1.9373939,"remaining_time":0.2894956402},
{"learn":[0.1243372956],"iteration":870,"passed_time":1.939470322,"remaining_time":0.2872464657},
{"learn":[0.1241449867],"iteration":871,"passed_time":1.941476987,"remaining_time":0.2849874476},
{"learn":[0.1240417021],"iteration":872,"passed_time":1.94354125,"remaining_time":0.2827373869},
{"learn":[0.1239375014],"iteration":873,"passed_time":1.945792047,"remaining_time":0.280514643},
{"learn":[0.1238131546],"iteration":874,"passed_time":1.948001418,"remaining_time":0.2782859169},
{"learn":[0.1237004402],"iteration":875,"passed_time":1.950246797,"remaining_time":0.2760623319},
{"learn":[0.12359688],"iteration":876,"passed_time":1.95252567,"remaining_time":0.2738433949},
{"learn":[0.1234294929],"iteration":877,"passed_time":1.954498921,"remaining_time":0.2715818546},
{"learn":[0.1233101646],"iteration":878,"passed_time":1.956690811,"remaining_time":0.2693510673},
{"learn":[0.1231708494],"iteration":879,"passed_time":1.958830465,"remaining_time":0.2671132452},
{"learn":[0.1230820572],"iteration":880,"passed_time":1.960840983,"remaining_time":0.2648582031},
{"learn":[0.1229249631],"iteration":881,"passed_time":1.962871623,"remaining_time":0.2626064076},
{"learn":[0.1228147708],"iteration":882,"passed_time":1.965421691,"remaining_time":0.2604239387},
{"learn":[0.1227651364],"iteration":883,"passed_time":1.967780174,"remaining_time":0.2582154979},
{"learn":[0.1226185578],"iteration":884,"passed_time":1.969891361,"remaining_time":0.2559745836},
{"learn":[0.1224994067],"iteration":885,"passed_time":1.97186756,"remaining_time":0.2537165935},
{"learn":[0.122313464],"iteration":886,"passed_time":1.974162439,"remaining_time":0.2514998372},
{"learn":[0.1221890476],"iteration":887,"passed_time":1.976366207,"remaining_time":0.2492714135},
{"learn":[0.1220743962],"iteration":888,"passed_time":1.978588989,"remaining_time":0.2470454193},
{"learn":[0.1218957068],"iteration":889,"passed_time":1.981036122,"remaining_time":0.2448471611},
{"learn":[0.1217057728],"iteration":890,"passed_time":1.983181844,"remaining_time":0.2426114714},
{"learn":[0.1216609751],"iteration":891,"passed_time":1.98518512,"remaining_time":0.2403587366},
{"learn":[0.1215612231],"iteration":892,"passed_time":1.987215095,"remaining_time":0.2381097595},
{"learn":[0.121475637],"iteration":893,"passed_time":1.989131871,"remaining_time":0.2358478505},
{"learn":[0.1213163689],"iteration":894,"passed_time":1.991224058,"remaining_time":0.2336072917},
{"learn":[0.1212262447],"iteration":895,"passed_time":1.993265208,"remaining_time":0.2313611403},
{"learn":[0.1211291296],"iteration":896,"passed_time":1.995410846,"remaining_time":0.2291274439},
{"learn":[0.1209741179],"iteration":897,"passed_time":1.997620558,"remaining_time":0.2269012215},
{"learn":[0.1209013908],"iteration":898,"passed_time":1.999607778,"remaining_time":0.2246500395},
{"learn":[0.1208617167],"iteration":899,"passed_time":2.001668052,"remaining_time":0.2224075614},
{"learn":[0.120726884],"iteration":900,"passed_time":2.003678119,"remaining_time":0.2201599709},
{"learn":[0.120623653],"iteration":901,"passed_time":2.005706901,"remaining_time":0.2179149404},
{"learn":[0.1205479946],"iteration":902,"passed_time":2.007686903,"remaining_time":0.2156651491},
{"learn":[0.1204442249],"iteration":903,"passed_time":2.009739759,"remaining_time":0.2134236912},
{"learn":[0.1203740342],"iteration":904,"passed_time":2.011897835,"remaining_time":0.2111936954},
{"learn":[0.120330576],"iteration":905,"passed_time":2.014234844,"remaining_time":0.2089824231},
{"learn":[0.1201704902],"iteration":906,"passed_time":2.016499192,"remaining_time":0.2067634232},
{"learn":[0.1200865486],"iteration":907,"passed_time":2.01864282,"remaining_time":0.2045320919},
{"learn":[0.1200743167],"iteration":908,"passed_time":2.020721947,"remaining_time":0.2022944963},
{"learn":[0.1199413579],"iteration":909,"passed_time":2.022808908,"remaining_time":0.2000580238},
{"learn":[0.1198364303],"iteration":910,"passed_time":2.024814135,"remaining_time":0.1978138947},
{"learn":[0.1197733798],"iteration":911,"passed_time":2.0268622,"remaining_time":0.1955744229},
{"learn":[0.1196829381],"iteration":912,"passed_time":2.029216418,"remaining_time":0.1933645437},
{"learn":[0.1196673512],"iteration":913,"passed_time":2.03154037,"remaining_time":0.1911515009},
{"learn":[0.119542724],"iteration":914,"passed_time":2.033569642,"remaining_time":0.1889108411},
{"learn":[0.1193684527],"iteration":915,"passed_time":2.035612049,"remaining_time":0.1866718473},
{"learn":[0.1192883743],"iteration":916,"passed_time":2.037729728,"remaining_time":0.1844400953},
{"learn":[0.1192077676],"iteration":917,"passed_time":2.039745717,"remaining_time":0.1821995085},
{"learn":[0.1190780536],"iteration":918,"passed_time":2.041898883,"remaining_time":0.1799715011},
{"learn":[0.1189533763],"iteration":919,"passed_time":2.043996669,"remaining_time":0.1777388408},
{"learn":[0.1188111757],"iteration":920,"passed_time":2.04610078,"remaining_time":0.1755070159},
{"learn":[0.1186860795],"iteration":921,"passed_time":2.048171197,"remaining_time":0.1732726176},
{"learn":[0.1185599759],"iteration":922,"passed_time":2.050236404,"remaining_time":0.1710381399},
{"learn":[0.1183425134],"iteration":923,"passed_time":2.052301559,"remaining_time":0.1688040243},
{"learn":[0.1181969828],"iteration":924,"passed_time":2.054305968,"remaining_time":0.1665653488},
{"learn":[0.117995672],"iteration":925,"passed_time":2.05656536,"remaining_time":0.1643475558},
{"learn":[0.1179155467],"iteration":926,"passed_time":2.058609853,"remaining_time":0.16211275},
{"learn":[0.1178194218],"iteration":927,"passed_time":2.061047414,"remaining_time":0.1599088511},
{"learn":[0.1177483799],"iteration":928,"passed_time":2.063524676,"remaining_time":0.1577074833},
{"learn":[0.1176054198],"iteration":929,"passed_time":2.066102995,"remaining_time":0.1555131286},
{"learn":[0.1175375411],"iteration":930,"passed_time":2.068199954,"remaining_time":0.1532822737},
{"learn":[0.1174416549],"iteration":931,"passed_time":2.070253974,"remaining_time":0.1510485732},
{"learn":[0.1172627983],"iteration":932,"passed_time":2.072333603,"remaining_time":0.1488170969},
{"learn":[0.1171409641],"iteration":933,"passed_time":2.074480483,"remaining_time":0.1465906979},
{"learn":[0.1170453908],"iteration":934,"passed_time":2.07680664,"remaining_time":0.1443769322},
{"learn":[0.116891684],"iteration":935,"passed_time":2.07889968,"remaining_time":0.1421469867},
{"learn":[0.1167928652],"iteration":936,"passed_time":2.080899289,"remaining_time":0.1399110514},
{"learn":[0.1166658753],"iteration":937,"passed_time":2.083013242,"remaining_time":0.1376831781},
{"learn":[0.1165332192],"iteration":938,"passed_time":2.085439366,"remaining_time":0.1354758268},
{"learn":[0.1163906849],"iteration":939,"passed_time":2.087478572,"remaining_time":0.1332433131},
{"learn":[0.116329279],"iteration":940,"passed_time":2.089659727,"remaining_time":0.1310201104},
{"learn":[0.1162758254],"iteration":941,"passed_time":2.091892713,"remaining_time":0.1288001883},
{"learn":[0.1161976732],"iteration":942,"passed_time":2.094413192,"remaining_time":0.126597616},
{"learn":[0.116166093],"iteration":943,"passed_time":2.096892189,"remaining_time":0.1243919095},
{"learn":[0.1160214243],"iteration":944,"passed_time":2.09917681,"remaining_time":0.1221743117},
{"learn":[0.1159767386],"iteration":945,"passed_time":2.10143341,"remaining_time":0.1199549727},
{"learn":[0.1158479555],"iteration":946,"passed_time":2.103768609,"remaining_time":0.1177399538},
{"learn":[0.1157844294],"iteration":947,"passed_time":2.105958934,"remaining_time":0.1155167348},
{"learn":[0.115642989],"iteration":948,"passed_time":2.10886105,"remaining_time":0.1133318373},
{"learn":[0.1155317142],"iteration":949,"passed_time":2.111303463,"remaining_time":0.1111212349},
{"learn":[0.115349538],"iteration":950,"passed_time":2.113360625,"remaining_time":0.1088902951},
{"learn":[0.1152679237],"iteration":951,"passed_time":2.115473096,"remaining_time":0.106662509},
{"learn":[0.1151432266],"iteration":952,"passed_time":2.117559695,"remaining_time":0.1044336891},
{"learn":[0.1150221002],"iteration":953,"passed_time":2.119827999,"remaining_time":0.1022139287},
{"learn":[0.1148833968],"iteration":954,"passed_time":2.122342593,"remaining_time":0.1000056719},
{"learn":[0.1147644022],"iteration":955,"passed_time":2.124780565,"remaining_time":0.09779324778},
{"learn":[0.1146639102],"iteration":956,"passed_time":2.127041807,"remaining_time":0.09557241137},
{"learn":[0.1145531695],"iteration":957,"passed_time":2.129323791,"remaining_time":0.09335240002},
{"learn":[0.1144647907],"iteration":958,"passed_time":2.131830893,"remaining_time":0.09114188385},
{"learn":[0.1143642636],"iteration":959,"passed_time":2.134041628,"remaining_time":0.08891840115},
{"learn":[0.114294231],"iteration":960,"passed_time":2.136317658,"remaining_time":0.08669759487},
{"learn":[0.1141905889],"iteration":961,"passed_time":2.138707273,"remaining_time":0.08448116047},
{"learn":[0.1141490861],"iteration":962,"passed_time":2.141328626,"remaining_time":0.08227327016},
{"learn":[0.1139944257],"iteration":963,"passed_time":2.143684416,"remaining_time":0.08005460476},
{"learn":[0.1139232348],"iteration":964,"passed_time":2.145688381,"remaining_time":0.07782289465},
{"learn":[0.1138455747],"iteration":965,"passed_time":2.147683262,"remaining_time":0.07559133636},
{"learn":[0.113705425],"iteration":966,"passed_time":2.149759438,"remaining_time":0.07336304182},
{"learn":[0.1135682152],"iteration":967,"passed_time":2.15178903,"remaining_time":0.07113352165},
{"learn":[0.1135133383],"iteration":968,"passed_time":2.154071937,"remaining_time":0.06891251809},
{"learn":[0.1134294091],"iteration":969,"passed_time":2.156362451,"remaining_time":0.06669162219},
{"learn":[0.1133622515],"iteration":970,"passed_time":2.158616671,"remaining_time":0.06446949892},
{"learn":[0.113168195],"iteration":971,"passed_time":2.160919338,"remaining_time":0.06224870522},
{"learn":[0.1129731091],"iteration":972,"passed_time":2.16330122,"remaining_time":0.06002994135},
{"learn":[0.1128015518],"iteration":973,"passed_time":2.165798395,"remaining_time":0.05781392018},
{"learn":[0.1126683702],"iteration":974,"passed_time":2.168178828,"remaining_time":0.05559432892},
{"learn":[0.1125825372],"iteration":975,"passed_time":2.17064055,"remaining_time":0.05337640697},
{"learn":[0.1124687003],"iteration":976,"passed_time":2.173109805,"remaining_time":0.05115816327},
{"learn":[0.1124198567],"iteration":977,"passed_time":2.175129544,"remaining_time":0.04892929445},
{"learn":[0.1122640223],"iteration":978,"passed_time":2.177286158,"remaining_time":0.04670378888},
{"learn":[0.1121038496],"iteration":979,"passed_time":2.179489559,"remaining_time":0.04447937875},
{"learn":[0.1119894458],"iteration":980,"passed_time":2.181845055,"remaining_time":0.04225795723},
{"learn":[0.1118262666],"iteration":981,"passed_time":2.184143674,"remaining_time":0.04003522009},
{"learn":[0.111692696],"iteration":982,"passed_time":2.186230399,"remaining_time":0.03780866407},
{"learn":[0.1115553867],"iteration":983,"passed_time":2.188599275,"remaining_time":0.03558698008},
{"learn":[0.1115011944],"iteration":984,"passed_time":2.190784213,"remaining_time":0.03336219614},
{"learn":[0.111364241],"iteration":985,"passed_time":2.193080677,"remaining_time":0.03113907655},
{"learn":[0.1112563135],"iteration":986,"passed_time":2.195190947,"remaining_time":0.02891335594},
{"learn":[0.1110783007],"iteration":987,"passed_time":2.197383364,"remaining_time":0.02668886677},
{"learn":[0.1109836609],"iteration":988,"passed_time":2.1996662,"remaining_time":0.02446544813},
{"learn":[0.1108830356],"iteration":989,"passed_time":2.202047064,"remaining_time":0.02224289963},
{"learn":[0.1107510984],"iteration":990,"passed_time":2.204502292,"remaining_time":0.02002070699},
{"learn":[0.1106242535],"iteration":991,"passed_time":2.20693847,"remaining_time":0.01779789089},
{"learn":[0.1104667652],"iteration":992,"passed_time":2.209092642,"remaining_time":0.01557265709},
{"learn":[0.1104172252],"iteration":993,"passed_time":2.211286622,"remaining_time":0.01334780657},
{"learn":[0.1102915688],"iteration":994,"passed_time":2.213342516,"remaining_time":0.0111223242},
{"learn":[0.1102298031],"iteration":995,"passed_time":2.215372524,"remaining_time":0.008897078411},
{"learn":[0.1101596329],"iteration":996,"passed_time":2.217491845,"remaining_time":0.006672493014},
{"learn":[0.1100310944],"iteration":997,"passed_time":2.220109195,"remaining_time":0.004449116623},
{"learn":[0.1099626065],"iteration":998,"passed_time":2.22265611,"remaining_time":0.002224880991},
{"learn":[0.1098387817],"iteration":999,"passed_time":2.224932086,"remaining_time":0}
]}